counter.v
//--------------------------------------------------------------
//  counter.v
//  -----------------------------------------------------------
//  功能 : 單一櫃台（Counter）之服務狀態機
//         ─ 收到 1-拍脈衝 ld=1 時，載入 {客人編號 dn, 服務時間 dt}
//         ─ busy=1 代表櫃台正在服務；rem 每拍倒數
//         ─ rem 歸零後自動釋放櫃台 (busy<=0) 並將輸出歸 0
//--------------------------------------------------------------
module counter(clk, rst_n, ld, dn, dt, busy, num, rem);
    parameter TIME_W = 4;          // 服務時間位元數，預設 4 bits

    //==================== 時脈 / 重設 =========================
    input  clk;                   // 系統時脈
    input  rst_n;                 // 同步低有效重設

    //==================== 新客人載入介面 ======================
    input         ld;             // 載入脈衝 (HIGH 1 拍)
    input  [3:0]  dn;             // data-num  : 客人編號
    input  [TIME_W-1:0] dt;       // data-time : 服務時間

    //==================== 狀態輸出 ===========================
    output reg        busy;       // =1，櫃台忙碌
    output reg [3:0]  num;        // 現正服務之客人編號	(idle=0)
    output reg [TIME_W-1:0] rem;  // 倒數剩餘時間		(idle=0)

	//--------------------------------------------------------------
	//  主時序區塊
	//  -----------------------------------------------------------
	//  ld=1   : 載入資料並進入忙碌狀態 (busy<=1)
	//  busy=1 : 每拍 rem--；倒數至 0 釋放櫃台 (busy<=0)
	//--------------------------------------------------------------
	always @(posedge clk or negedge rst_n) begin
		if (!rst_n) begin
			// ---------- 非同步重設 --------------------------------
			busy <= 1'b0;
			num  <= 4'd0;
			rem  <= {TIME_W{1'b0}};
		end
		else begin
			if (ld) begin
				// ---------- 進入服務 -------------------------------
				busy <= 1'b1;
				num  <= dn;
				rem  <= dt;
			end
			else if (busy) begin
				// ---------- 服務進行中：倒數 -----------------------
				if (rem > 1)
					rem <= rem - 1'b1;          // 尚未完成
				else begin
					// rem==1 : 下一拍歸 0，釋放櫃台
					busy <= 1'b0;
					num  <= 4'd0;
					rem  <= {TIME_W{1'b0}};
				end
			end
			// idle 狀態 (busy=0 且 ld=0) : 保持輸出為 0
		end
	end
endmodule

dispatcher.v
//--------------------------------------------------------------
//  dispatcher.v
//  -----------------------------------------------------------
//  1. 功能 : 從佇列 FIFO 取出一筆資料，依序派發給
//            第一個「空閒」的櫃檯 (counter)。
//  2. 規則 : 固定優先權  櫃檯1 → 櫃檯2 → 櫃檯3
//            只要成功派發，就對 FIFO 送出 re=1 讀脈衝。
//  3. 時序 : 以 clk 正緣為基準，所有旗標皆同步重設。
//--------------------------------------------------------------
module dispatcher(clk, rst_n, empty, busy, qn, qt, re, ld1, ld2, ld3, dn1, dt1, dn2, dt2, dn3, dt3);
    //==================== 時脈 / 重設 =========================
    input  clk;
    input  rst_n;              // 同步低有效

    //==================== 來自 FIFO 的訊號 =====================
    input        empty;        // =1 代表 FIFO 為空
    input  [3:0] qn;           // 佇列首端客人編號
    input  [3:0] qt;           // 佇列首端服務時間

    //==================== 各櫃檯忙碌狀態 ======================
    // busy[i] = 1 → 該櫃檯正在服務，不可派發
    input  [2:0] busy;

    //==================== 給 FIFO 的控制 ======================
    output reg   re;           // 讀出脈衝 (HIGH 1 個 clk)

    //==================== 給三個 counter 的載入控制 ===========
    // ld?  : 載入脈衝 (HIGH 1 個 clk)
    // dn?/dt? : 欲載入之 {編號, 時間}
    output reg   ld1, ld2, ld3;
    output reg [3:0] dn1, dn2, dn3;
    output reg [3:0] dt1, dt2, dt3;

	//--------------------------------------------------------------
	//  派發邏輯
	//--------------------------------------------------------------
	always @(posedge clk or negedge rst_n) begin
		if (!rst_n) begin
			// --------- 非同步重設 ---------------------------------
			re  <= 1'b0;
			ld1 <= 1'b0;  dn1 <= 4'd0;  dt1 <= 4'd0;
			ld2 <= 1'b0;  dn2 <= 4'd0;  dt2 <= 4'd0;
			ld3 <= 1'b0;  dn3 <= 4'd0;  dt3 <= 4'd0;
		end
		else begin
			// --------- 預設值：每拍先清脈衝 ------------------------
			re  <= 1'b0;
			ld1 <= 1'b0;  ld2 <= 1'b0;  ld3 <= 1'b0;

			// --------- 當 FIFO 非空，嘗試派發 ----------------------
			if (!empty) begin
				// --- 優先檢查櫃檯1 ---------------------------------
				if (!busy[0]) begin
					re  <= 1'b1;        // 讀出 FIFO
					ld1 <= 1'b1;        // 觸發櫃檯1 載入
					dn1 <= qn;          // 資料送入櫃檯1
					dt1 <= qt;
				end
				// --- 再檢查櫃檯2 -----------------------------------
				else if (!busy[1]) begin
					re  <= 1'b1;
					ld2 <= 1'b1;
					dn2 <= qn;
					dt2 <= qt;
				end
				// --- 最後檢查櫃檯3 ---------------------------------
				else if (!busy[2]) begin
					re  <= 1'b1;
					ld3 <= 1'b1;
					dn3 <= qn;
					dt3 <= qt;
				end
				// 若全忙碌：不派發，re=0，資料留在 FIFO
			end
		end
	end
endmodule

queue.v
//--------------------------------------------------------------
//  queue.v  -  簡易參數化 FIFO（深度 DEPTH，預設 3）
//  - 用於暫存尚未被派發到櫃檯的客人資料
//  - 每筆資料包含 {客人編號 4-bit, 服務時間 4-bit}
//--------------------------------------------------------------
module queue(clk, rst_n, we, dn, dt, re, qn, qt, full, empty, qdbg);
    parameter DT_SZ = 4;					// 資料大小，預設 4 bits
    parameter DEPTH = 3;					// 佇列深度
    parameter PTR_W = 2;          			// PTR_W = (int)(log2(DEPTH))+1
	// DEPTH = 3 時，PTR_W 固定 2 bit

    input  clk;                          	// 系統時脈
    input  rst_n;                        	// 同步低有效重設

    // 寫入端 (enqueue)
    input         		we;                 // we=1 且 ~full 時寫入
    input  [DT_SZ-1:0]  dn;                 // data-num  : 客人編號
    input  [DT_SZ-1:0]  dt;                 // data-time : 服務時間
    
	// 讀出端 (dequeue)
    input         		re;                 // re=1 且 ~empty 時讀出
    output [DT_SZ-1:0]  qn;                 // queue-num  : 佇列首端客人編號
    output [DT_SZ-1:0]  qt;                 // queue-time : 佇列首端服務時間
    
	// 狀態旗標
    output full;                            // 佇列已滿
    output empty;                           // 佇列為空
    
	//--------------------------------------------------------------
	//  內部儲存結構
	//--------------------------------------------------------------
	reg [DT_SZ-1:0] nm [0:DEPTH-1];   // 編號暫存
	reg [DT_SZ-1:0] tm [0:DEPTH-1];   // 時間暫存

	reg [PTR_W-1:0] hd;   // head 讀指標
	reg [PTR_W-1:0] tl;   // tail 寫指標
	reg [PTR_W-1:0] ct;   // 佇列目前元素數 (0-DEPTH)

	//--------------------------------------------------------------
	//  即時輸出
	//--------------------------------------------------------------
	assign qn    = nm[hd];               // 讀指標指向的資料
	assign qt    = tm[hd];
	assign full  = (ct == DEPTH);        // 已填滿
	assign empty = (ct == 0);            // 沒有資料
	
	// for 迴圈用
	integer i;

	// 串接資料供波形觀察
    output reg [DEPTH*2*DT_SZ-1:0] qdbg;
    always @(hd or tl) begin
		qdbg = {DEPTH*2*DT_SZ{1'b0}};
        for(i = 0; i < ct; i = i + 1) begin
            qdbg = {qdbg, nm[(hd+i)%DEPTH], tm[(hd+i)%DEPTH]};
        end
		for(     ; i < DEPTH; i = i + 1) begin
            qdbg = {qdbg, 8'd0};
		end
    end

	//--------------------------------------------------------------
	//  寫入 / 讀出 控制邏輯
	//--------------------------------------------------------------
	always @(posedge clk or negedge rst_n) begin
		if (!rst_n) begin
			hd <= 0;
			tl <= 0;
			ct <= 0;
			for (i = 0; i < DEPTH; i = i + 1) begin
				nm[i] <= {DT_SZ{1'b0}};      // 編號清 0
				tm[i] <= {DT_SZ{1'b0}};      // 時間清 0
        	end
		end
		else begin
			// 寫入動作 ------------------------------------------------
			if (we && !full) begin
				nm[tl] <= dn;
				tm[tl] <= dt;
				tl <= (tl == DEPTH-1) ? 0 : tl + 1;   // 環形遞增
			end

			// 讀出動作 ------------------------------------------------
			if (re && !empty) begin
				hd <= (hd == DEPTH-1) ? 0 : hd + 1;   // 環形遞增
			end

			// 元素計數器 --------------------------------------------
			case ({we && !full, re && !empty})
				2'b10: ct <= ct + 1;   // 只有寫入
				2'b01: ct <= ct - 1;   // 只有讀出
				default: ;             // 其餘情況 ct 不變
			endcase
		end
	end
endmodule

top.v
//--------------------------------------------------------------
//  top.v  -  Queue / Dispatcher / Counter 整合測試平台
//           (針對 ISE Design Suite 14.7 產生)
//--------------------------------------------------------------
//  系統概要：
//  -----------------------------------------------------------
//  1. 來源：外部會以 in_valid=1 送入 {客人編號 in_num[3:0], 服務時間 in_time[3:0]}
//  2. 流程：
//      2-1. queue   : 尚無櫃檯可用時，資料先進 FIFO (深度=3)
//      2-2. dispatcher : 偵測空櫃檯，從 queue 取值派發 (固定優先權 櫃檯1->2->3)
//      2-3. counter : 櫃檯內部倒數；完成後自動 idle
//  3. 輸出：
//      num1/clk1 ... num3/clk3   : 各櫃檯現正服務客人編號 / 剩餘倒數
//      queue                     : FIFO 內容除錯觀察 (24-bit)
//--------------------------------------------------------------
module top(clk, rst_n, in_valid, in_num, in_time, num1, clk1, num2, clk2, num3, clk3, 
			qdbg); // debug
    //==================== 時脈 / 重設 =========================
    input  clk;                   // 20 ns 週期 (50 MHz)
    input  rst_n;                 // 同步低有效

    //==================== 來源輸入 ============================
    input         in_valid;       // =1 時 in_num / in_time 有效
    input  [3:0]  in_num;         // 客人編號 (0 為空)
    input  [3:0]  in_time;        // 服務時間 (1~7)

    //==================== 櫃檯狀態輸出 ========================
    output [3:0]  num1;           // 櫃檯1 現正服務客人
    output [3:0]  clk1;           // 櫃檯1 剩餘時間
    output [3:0]  num2;
    output [3:0]  clk2;
    output [3:0]  num3;
    output [3:0]  clk3;

    //==================== FIFO 佇列除錯用 ====================
	// 除錯觀察用
    output [23:0] qdbg;

	//--------------------------------------------------------------
	//  內部線路宣告
	//--------------------------------------------------------------
	wire        fifo_re;              // dispatcher 對 FIFO 的讀脈衝
	wire        ld1, ld2, ld3;        // dispatcher -> counter 的載入
	wire [2:0]  busy;                 // counters 忙碌旗標
	wire        fifo_full, fifo_emp;  // FIFO 滿 / 空
	wire [3:0]  fifo_num;             // queue 輸出編號
	wire [3:0]  fifo_tim;             // queue 輸出時間
	wire [3:0]  dn1, dn2, dn3;        // 發送至 counter 的編號
	wire [3:0]  dt1, dt2, dt3;        // 發送至 counter 的時間

	//--------------------------------------------------------------
	//  模組例化
	//--------------------------------------------------------------
	//  1. 佇列 FIFO ---------------------------------------------
	// in_valid = 1，上層總是嘗試寫入，queue 內部會判斷 full
	// 深度固定為 3 (可參數化)
	queue #(3) u_queue (
		clk, rst_n, in_valid, in_num, in_time, 
		fifo_re, fifo_num, fifo_tim, fifo_full, fifo_emp, 
		qdbg); // debug

	//  2. 調度器 Dispatcher -------------------------------------
	// busy = {b3,b2,b1}
	dispatcher u_disp (
		clk, rst_n, fifo_emp, busy, fifo_num, fifo_tim, fifo_re, 
		ld1, ld2, ld3, dn1, dt1, dn2, dt2, dn3, dt3);

	//  3. 三個櫃檯 Counter --------------------------------------
	//      counter#1
	counter u_c1 (clk, rst_n, ld1, dn1, dt1, busy[0], num1, clk1);
	//      counter#2
	counter u_c2 (clk, rst_n, ld2, dn2, dt2, busy[1], num2, clk2);
	//      counter#3
	counter u_c3 (clk, rst_n, ld3, dn3, dt3, busy[2], num3, clk3);
endmodule

top_tb.v
`timescale 1ns / 1ps
module top_tb;

	// Inputs
	reg clk;
	reg rst_n;
	reg in_valid;
	reg [3:0] in_num;
	reg [3:0] in_time;

	// Outputs
	wire [3:0] num1;
	wire [3:0] clk1;
	wire [3:0] num2;
	wire [3:0] clk2;
	wire [3:0] num3;
	wire [3:0] clk3;
	wire [23:0] qdbg;
	
	// Instantiate the Unit Under Test (UUT)
	top uut (
		.clk(clk), 
		.rst_n(rst_n), 
		.in_valid(in_valid), 
		.in_num(in_num), 
		.in_time(in_time), 
		.num1(num1), 
		.clk1(clk1), 
		.num2(num2), 
		.clk2(clk2), 
		.num3(num3), 
		.clk3(clk3), 
		.qdbg(qdbg)
	);

//==== Clock : 20 ns 週期 ======================================
always #10 clk = ~clk;

//==== Reset ===================================================
initial begin
    clk = 0;
    rst_n = 0;
    in_valid = 0;
    in_num = 0;
    in_time = 0;
    #35 rst_n = 1;           // 釋放重設
end

//==== 送客人 Task =============================================
task send_cust;
    input [7:0] num;
    input [2:0] tim;
begin
    @(negedge clk);
    in_valid = 1;
    in_num   = num;
    in_time  = tim;
    @(negedge clk);
    in_valid = 0;
    in_num   = 0;
    in_time  = 0;
end
endtask

//==== Stimulus ================================================
initial begin
    @(posedge rst_n);        // 等待重設結束
    #20;

    // ── 先填滿三個櫃台 ───────────────────────────────
    send_cust(4'd1, 4'd3);
    send_cust(4'd2, 4'd2);
    send_cust(4'd3, 4'd4);

    // ── 再塞進 FIFO（深度 3）────────────────────────
    send_cust(4'd4, 4'd1);
    send_cust(4'd5, 4'd5);
    send_cust(4'd6, 4'd2);

    // ── 佇列已滿，以下客人應被丟棄 ──────────────────
    send_cust(4'd7, 4'd3);

    // ── 等待部分櫃台釋放，再送新客人 ────────────────
    #500;
    send_cust(4'd8, 4'd2);
    send_cust(4'd9, 4'd6);

    // ── 結束模擬 ───────────────────────────────────
    #1000 $finish;
end

//==== 波形輸出 (VCD) ==========================================
initial begin
    $dumpfile("top_tb.vcd");
    $dumpvars(0, top_tb);
end

endmodule

top_tb.vcd
$date
   Thu May 29 20:21:16 2025
$end
$version
  P.20131013
$end
$timescale
  1ps
$end
$scope module top_tb $end
$var wire 1 c num1 [3] $end
$var wire 1 d num1 [2] $end
$var wire 1 e num1 [1] $end
$var wire 1 f num1 [0] $end
$var wire 1 g clk1 [3] $end
$var wire 1 h clk1 [2] $end
$var wire 1 i clk1 [1] $end
$var wire 1 j clk1 [0] $end
$var wire 1 k num2 [3] $end
$var wire 1 l num2 [2] $end
$var wire 1 m num2 [1] $end
$var wire 1 n num2 [0] $end
$var wire 1 o clk2 [3] $end
$var wire 1 p clk2 [2] $end
$var wire 1 q clk2 [1] $end
$var wire 1 r clk2 [0] $end
$var wire 1 s num3 [3] $end
$var wire 1 t num3 [2] $end
$var wire 1 u num3 [1] $end
$var wire 1 v num3 [0] $end
$var wire 1 w clk3 [3] $end
$var wire 1 x clk3 [2] $end
$var wire 1 y clk3 [1] $end
$var wire 1 z clk3 [0] $end
$var wire 1 t! qdbg [23] $end
$var wire 1 u! qdbg [22] $end
$var wire 1 v! qdbg [21] $end
$var wire 1 w! qdbg [20] $end
$var wire 1 x! qdbg [19] $end
$var wire 1 y! qdbg [18] $end
$var wire 1 z! qdbg [17] $end
$var wire 1 {! qdbg [16] $end
$var wire 1 |! qdbg [15] $end
$var wire 1 }! qdbg [14] $end
$var wire 1 ~! qdbg [13] $end
$var wire 1 !" qdbg [12] $end
$var wire 1 "" qdbg [11] $end
$var wire 1 #" qdbg [10] $end
$var wire 1 $" qdbg [9] $end
$var wire 1 %" qdbg [8] $end
$var wire 1 &" qdbg [7] $end
$var wire 1 '" qdbg [6] $end
$var wire 1 (" qdbg [5] $end
$var wire 1 )" qdbg [4] $end
$var wire 1 *" qdbg [3] $end
$var wire 1 +" qdbg [2] $end
$var wire 1 ," qdbg [1] $end
$var wire 1 -" qdbg [0] $end
$var reg 1 Q clk $end
$var reg 1 R rst_n $end
$var reg 1 S in_valid $end
$var reg 4 T in_num [3:0] $end
$var reg 4 U in_time [3:0] $end
$scope task send_cust $end
$var reg 8 V num [7:0] $end
$var reg 3 W tim [2:0] $end
$upscope $end
$scope module uut $end
$var wire 1 h" clk $end
$var wire 1 i" rst_n $end
$var wire 1 `! in_valid $end
$var wire 1 a! in_num [3] $end
$var wire 1 b! in_num [2] $end
$var wire 1 c! in_num [1] $end
$var wire 1 d! in_num [0] $end
$var wire 1 e! in_time [3] $end
$var wire 1 f! in_time [2] $end
$var wire 1 g! in_time [1] $end
$var wire 1 h! in_time [0] $end
$var wire 1 c num1 [3] $end
$var wire 1 d num1 [2] $end
$var wire 1 e num1 [1] $end
$var wire 1 f num1 [0] $end
$var wire 1 g clk1 [3] $end
$var wire 1 h clk1 [2] $end
$var wire 1 i clk1 [1] $end
$var wire 1 j clk1 [0] $end
$var wire 1 k num2 [3] $end
$var wire 1 l num2 [2] $end
$var wire 1 m num2 [1] $end
$var wire 1 n num2 [0] $end
$var wire 1 o clk2 [3] $end
$var wire 1 p clk2 [2] $end
$var wire 1 q clk2 [1] $end
$var wire 1 r clk2 [0] $end
$var wire 1 s num3 [3] $end
$var wire 1 t num3 [2] $end
$var wire 1 u num3 [1] $end
$var wire 1 v num3 [0] $end
$var wire 1 w clk3 [3] $end
$var wire 1 x clk3 [2] $end
$var wire 1 y clk3 [1] $end
$var wire 1 z clk3 [0] $end
$var wire 1 t! qdbg [23] $end
$var wire 1 u! qdbg [22] $end
$var wire 1 v! qdbg [21] $end
$var wire 1 w! qdbg [20] $end
$var wire 1 x! qdbg [19] $end
$var wire 1 y! qdbg [18] $end
$var wire 1 z! qdbg [17] $end
$var wire 1 {! qdbg [16] $end
$var wire 1 |! qdbg [15] $end
$var wire 1 }! qdbg [14] $end
$var wire 1 ~! qdbg [13] $end
$var wire 1 !" qdbg [12] $end
$var wire 1 "" qdbg [11] $end
$var wire 1 #" qdbg [10] $end
$var wire 1 $" qdbg [9] $end
$var wire 1 %" qdbg [8] $end
$var wire 1 &" qdbg [7] $end
$var wire 1 '" qdbg [6] $end
$var wire 1 (" qdbg [5] $end
$var wire 1 )" qdbg [4] $end
$var wire 1 *" qdbg [3] $end
$var wire 1 +" qdbg [2] $end
$var wire 1 ," qdbg [1] $end
$var wire 1 -" qdbg [0] $end
$var wire 1 i! fifo_re $end
$var wire 1 N" ld1 $end
$var wire 1 \" ld2 $end
$var wire 1 j" ld3 $end
$var wire 1 ?" busy [2] $end
$var wire 1 @" busy [1] $end
$var wire 1 A" busy [0] $end
$var wire 1 r! fifo_full $end
$var wire 1 6" fifo_emp $end
$var wire 1 7" fifo_num [3] $end
$var wire 1 8" fifo_num [2] $end
$var wire 1 9" fifo_num [1] $end
$var wire 1 :" fifo_num [0] $end
$var wire 1 ;" fifo_tim [3] $end
$var wire 1 <" fifo_tim [2] $end
$var wire 1 =" fifo_tim [1] $end
$var wire 1 >" fifo_tim [0] $end
$var wire 1 O" dn1 [3] $end
$var wire 1 P" dn1 [2] $end
$var wire 1 Q" dn1 [1] $end
$var wire 1 R" dn1 [0] $end
$var wire 1 ]" dn2 [3] $end
$var wire 1 ^" dn2 [2] $end
$var wire 1 _" dn2 [1] $end
$var wire 1 `" dn2 [0] $end
$var wire 1 k" dn3 [3] $end
$var wire 1 l" dn3 [2] $end
$var wire 1 m" dn3 [1] $end
$var wire 1 n" dn3 [0] $end
$var wire 1 S" dt1 [3] $end
$var wire 1 T" dt1 [2] $end
$var wire 1 U" dt1 [1] $end
$var wire 1 V" dt1 [0] $end
$var wire 1 a" dt2 [3] $end
$var wire 1 b" dt2 [2] $end
$var wire 1 c" dt2 [1] $end
$var wire 1 d" dt2 [0] $end
$var wire 1 o" dt3 [3] $end
$var wire 1 p" dt3 [2] $end
$var wire 1 q" dt3 [1] $end
$var wire 1 r" dt3 [0] $end
$scope module u_queue $end
$var wire 1 h" clk $end
$var wire 1 i" rst_n $end
$var wire 1 `! we $end
$var wire 1 a! dn [3] $end
$var wire 1 b! dn [2] $end
$var wire 1 c! dn [1] $end
$var wire 1 d! dn [0] $end
$var wire 1 e! dt [3] $end
$var wire 1 f! dt [2] $end
$var wire 1 g! dt [1] $end
$var wire 1 h! dt [0] $end
$var wire 1 i! re $end
$var wire 1 7" qn [3] $end
$var wire 1 8" qn [2] $end
$var wire 1 9" qn [1] $end
$var wire 1 :" qn [0] $end
$var wire 1 ;" qt [3] $end
$var wire 1 <" qt [2] $end
$var wire 1 =" qt [1] $end
$var wire 1 >" qt [0] $end
$var wire 1 r! full $end
$var wire 1 6" empty $end
$var wire 1 t! qdbg [23] $end
$var wire 1 u! qdbg [22] $end
$var wire 1 v! qdbg [21] $end
$var wire 1 w! qdbg [20] $end
$var wire 1 x! qdbg [19] $end
$var wire 1 y! qdbg [18] $end
$var wire 1 z! qdbg [17] $end
$var wire 1 {! qdbg [16] $end
$var wire 1 |! qdbg [15] $end
$var wire 1 }! qdbg [14] $end
$var wire 1 ~! qdbg [13] $end
$var wire 1 !" qdbg [12] $end
$var wire 1 "" qdbg [11] $end
$var wire 1 #" qdbg [10] $end
$var wire 1 $" qdbg [9] $end
$var wire 1 %" qdbg [8] $end
$var wire 1 &" qdbg [7] $end
$var wire 1 '" qdbg [6] $end
$var wire 1 (" qdbg [5] $end
$var wire 1 )" qdbg [4] $end
$var wire 1 *" qdbg [3] $end
$var wire 1 +" qdbg [2] $end
$var wire 1 ," qdbg [1] $end
$var wire 1 -" qdbg [0] $end
$var reg 12 ." nm [3:0] $end
$var reg 12 /" tm [3:0] $end
$var reg 2 0" hd [1:0] $end
$var reg 2 1" tl [1:0] $end
$var reg 2 2" ct [1:0] $end
$var integer 32 3" i $end
$upscope $end
$scope module u_disp $end
$var wire 1 h" clk $end
$var wire 1 i" rst_n $end
$var wire 1 6" empty $end
$var wire 1 7" qn [3] $end
$var wire 1 8" qn [2] $end
$var wire 1 9" qn [1] $end
$var wire 1 :" qn [0] $end
$var wire 1 ;" qt [3] $end
$var wire 1 <" qt [2] $end
$var wire 1 =" qt [1] $end
$var wire 1 >" qt [0] $end
$var wire 1 ?" busy [2] $end
$var wire 1 @" busy [1] $end
$var wire 1 A" busy [0] $end
$var reg 1 B" re $end
$var reg 1 C" ld1 $end
$var reg 1 D" ld2 $end
$var reg 1 E" ld3 $end
$var reg 4 F" dn1 [3:0] $end
$var reg 4 G" dn2 [3:0] $end
$var reg 4 H" dn3 [3:0] $end
$var reg 4 I" dt1 [3:0] $end
$var reg 4 J" dt2 [3:0] $end
$var reg 4 K" dt3 [3:0] $end
$upscope $end
$scope module u_c1 $end
$var wire 1 h" clk $end
$var wire 1 i" rst_n $end
$var wire 1 N" ld $end
$var wire 1 O" dn [3] $end
$var wire 1 P" dn [2] $end
$var wire 1 Q" dn [1] $end
$var wire 1 R" dn [0] $end
$var wire 1 S" dt [3] $end
$var wire 1 T" dt [2] $end
$var wire 1 U" dt [1] $end
$var wire 1 V" dt [0] $end
$var reg 1 W" busy $end
$var reg 4 X" num [3:0] $end
$var reg 4 Y" rem [3:0] $end
$upscope $end
$scope module u_c2 $end
$var wire 1 h" clk $end
$var wire 1 i" rst_n $end
$var wire 1 \" ld $end
$var wire 1 ]" dn [3] $end
$var wire 1 ^" dn [2] $end
$var wire 1 _" dn [1] $end
$var wire 1 `" dn [0] $end
$var wire 1 a" dt [3] $end
$var wire 1 b" dt [2] $end
$var wire 1 c" dt [1] $end
$var wire 1 d" dt [0] $end
$var reg 1 e" busy $end
$var reg 4 f" num [3:0] $end
$var reg 4 g" rem [3:0] $end
$upscope $end
$scope module u_c3 $end
$var wire 1 h" clk $end
$var wire 1 i" rst_n $end
$var wire 1 j" ld $end
$var wire 1 k" dn [3] $end
$var wire 1 l" dn [2] $end
$var wire 1 m" dn [1] $end
$var wire 1 n" dn [0] $end
$var wire 1 o" dt [3] $end
$var wire 1 p" dt [2] $end
$var wire 1 q" dt [1] $end
$var wire 1 r" dt [0] $end
$var reg 1 s" busy $end
$var reg 4 t" num [3:0] $end
$var reg 4 u" rem [3:0] $end
$upscope $end
$upscope $end
$upscope $end
$enddefinitions $end
#0
$dumpvars
0e
0f
0b!
0f!
0a!
0`!
0d!
0e!
0g!
0h!
0c!
0d
0c
0j
0i
0h
0g
0n
0m
0l
0k
0r
0q
0p
0Q
0R
0S
b0 T
b0 U
bx V
bx W
0+"
0*"
0u
0)"
0-"
0("
0'"
0o
0&"
0,"
0v
0t
0x
0s
0z
0w
0y
0\"
0:"
0x!
0w!
0="
0y!
0v!
0#"
0N"
08"
0%"
0}!
0~!
0|!
0t!
0!"
09"
0?"
0""
0i!
0j"
0$"
0z!
0@"
0r!
07"
0>"
0<"
0u!
0A"
0;"
0R"
0{!
0Q"
0P"
16"
0S"
0T"
0l"
0q"
0n"
0k"
0O"
0h"
0]"
0d"
0m"
0a"
0`"
0c"
0o"
0_"
0U"
0V"
0r"
0^"
0p"
0b"
0i"
b0 ."
b0 /"
b0 0"
b0 1"
b0 2"
b11 3"
0B"
0C"
0D"
0E"
b0 F"
b0 G"
b0 H"
b0 I"
b0 J"
b0 K"
0W"
b0 X"
b0 Y"
0e"
b0 f"
b0 g"
0s"
b0 t"
b0 u"
$end
#10000
1Q
1h"
b11 3"
#20000
0Q
0h"
#30000
1Q
1h"
b11 3"
#35000
1R
1i"
#40000
0Q
0h"
#50000
1Q
1h"
#55000
b1 V
b11 W
#60000
1`!
1d!
1g!
1h!
0Q
1S
b1 T
b11 U
0h"
#70000
1Q
1:"
1w!
1="
1z!
1>"
1{!
06"
1h"
b100000000 ."
b1100000000 /"
b1 1"
b1 2"
#80000
0`!
0d!
0g!
0h!
0Q
0S
b0 T
b0 U
b10 V
b10 W
0h"
#90000
1Q
1N"
1i!
1R"
1h"
1U"
1V"
1B"
1C"
b1 F"
b11 I"
#100000
1`!
1g!
1c!
0Q
1S
b10 T
b10 U
0h"
#110000
1f
1j
1i
1Q
0:"
1~!
19"
1$"
0>"
1A"
1h"
b100100000 ."
b1100100000 /"
b1 0"
b10 1"
1B"
1C"
1W"
b1 X"
b11 Y"
#120000
0`!
0g!
0c!
0Q
0S
b0 T
b0 U
b11 V
b100 W
0h"
#130000
1Q
1\"
0="
0N"
09"
16"
1h"
1c"
1_"
b10 0"
b0 2"
1B"
0C"
1D"
b10 G"
b10 J"
#140000
1f!
1`!
1d!
1c!
0Q
1S
b11 T
b100 U
0h"
#150000
0j
1m
1q
1Q
1+"
1)"
1("
0\"
1:"
19"
0i!
1@"
1<"
06"
1h"
b100100011 ."
b1100100100 /"
b0 1"
b1 2"
0B"
0D"
b10 Y"
1e"
b10 f"
b10 g"
#160000
0f!
0`!
0d!
0c!
0Q
0S
b0 T
b0 U
b100 V
b1 W
0h"
#170000
1j
0i
1r
0q
1Q
1i!
1j"
1n"
1h"
1m"
1p"
1B"
1E"
b11 H"
b100 K"
b1 Y"
b1 g"
#180000
1b!
1`!
1h!
0Q
1S
b100 T
b1 U
0h"
#190000
0f
0j
0m
0r
1Q
1u
1v
1x
0:"
0w!
18"
09"
1?"
0z!
0@"
1>"
0<"
1u!
0A"
1h"
b10000100011 ."
b100100100 /"
b0 0"
b1 1"
1B"
1E"
0W"
b0 X"
b0 Y"
0e"
b0 f"
b0 g"
1s"
b11 t"
b100 u"
#200000
0b!
0`!
0h!
0Q
0S
b0 T
b0 U
b101 V
b101 W
0h"
#210000
1Q
1="
1N"
08"
19"
0j"
0>"
0R"
1P"
16"
1h"
0U"
b1 0"
b0 2"
1B"
1C"
0E"
b100 F"
b1 I"
#220000
1b!
1f!
1`!
1d!
1h!
0Q
1S
b101 T
b101 U
0h"
#230000
1d
1j
1Q
0x
1z
1y
1:"
0="
1#"
0N"
18"
1%"
1}!
0~!
1!"
09"
0i!
0$"
1>"
1<"
1A"
06"
1h"
b10001010011 ."
b101010100 /"
b10 1"
b1 2"
0B"
0C"
1W"
b100 X"
b1 Y"
b11 u"
#240000
0b!
0f!
0`!
0d!
0h!
0Q
0S
b0 T
b0 U
b110 V
b10 W
0h"
#250000
0d
0j
1Q
0z
1\"
1i!
0A"
1h"
1d"
1`"
0c"
0_"
1^"
1b"
1B"
1D"
b101 G"
b101 J"
0W"
b0 X"
b0 Y"
b10 u"
#260000
1b!
1`!
1g!
1c!
0Q
1S
b110 T
b10 U
0h"
#270000
1n
1l
1r
1p
1Q
0+"
0)"
1'"
1,"
1z
0y
0\"
0:"
1="
1N"
19"
1@"
0>"
0<"
1R"
1T"
1h"
b10001010110 ."
b101010010 /"
b10 0"
b0 1"
1B"
1C"
0D"
b101 F"
b101 I"
1e"
b101 f"
b101 g"
b1 u"
#280000
0b!
0`!
0g!
0c!
0Q
0S
b0 T
b0 U
b111 V
b11 W
0h"
#290000
1f
1d
1j
1h
0r
1Q
0u
0v
0z
0="
09"
0?"
1>"
1A"
0R"
1Q"
16"
0T"
1h"
1U"
0V"
b0 0"
b0 2"
1B"
1C"
b110 F"
b10 I"
1W"
b101 X"
b101 Y"
b100 g"
0s"
b0 t"
b0 u"
#300000
1b!
1`!
1d!
1g!
1h!
1c!
0Q
1S
b111 T
b11 U
0h"
#310000
1e
0f
0j
1i
0h
1r
1q
0p
1Q
1:"
1w!
1="
1v!
0N"
19"
0i!
1z!
06"
1h"
b11101010110 ."
b1101010010 /"
b1 1"
b1 2"
0B"
0C"
b110 X"
b10 Y"
b11 g"
#320000
0b!
0`!
0d!
0g!
0h!
0c!
0Q
0S
b0 T
b0 U
0h"
#330000
1j
0i
0r
1Q
1i!
1j"
1l"
1q"
1h"
1r"
0p"
1B"
1E"
b111 H"
b11 K"
b1 Y"
b10 g"
#340000
0Q
0h"
#350000
0e
0d
0j
1r
0q
1Q
1u
1v
1t
1z
1y
0="
09"
1?"
1<"
0A"
16"
1h"
b1 0"
b0 2"
1B"
1E"
0W"
b0 X"
b0 Y"
b1 g"
1s"
b111 t"
b11 u"
#360000
0Q
0h"
#370000
0n
0l
0r
1Q
0i!
0j"
0@"
1h"
0B"
0E"
0e"
b0 f"
b0 g"
#380000
0Q
0h"
#390000
1Q
0z
1h"
b10 u"
#400000
0Q
0h"
#410000
1Q
1z
0y
1h"
b1 u"
#420000
0Q
0h"
#430000
1Q
0u
0v
0t
0z
0?"
1h"
0s"
b0 t"
b0 u"
#440000
0Q
0h"
#450000
1Q
1h"
#460000
0Q
0h"
#470000
1Q
1h"
#480000
0Q
0h"
#490000
1Q
1h"
#500000
0Q
0h"
#510000
1Q
1h"
#520000
0Q
0h"
#530000
1Q
1h"
#540000
0Q
0h"
#550000
1Q
1h"
#560000
0Q
0h"
#570000
1Q
1h"
#580000
0Q
0h"
