counter.v
//--------------------------------------------------------------
//  counter.v
//  -----------------------------------------------------------
//  功能 : 單一櫃台（Counter）之服務狀態機
//         ─ 收到 1-拍脈衝 ld=1 時，載入 {客人編號 dn, 服務時間 dt}
//         ─ busy=1 代表櫃台正在服務；rem 每拍倒數
//         ─ rem 歸零後自動釋放櫃台 (busy<=0) 並將輸出歸 0
//--------------------------------------------------------------
module counter(clk, rst_n, ld, dn, dt, busy, num, rem);
    parameter TIME_W = 4;          // 服務時間位元數，預設 4 bits

    //==================== 時脈 / 重設 =========================
    input  clk;                   // 系統時脈
    input  rst_n;                 // 同步低有效重設

    //==================== 新客人載入介面 ======================
    input         ld;             // 載入脈衝 (HIGH 1 拍)
    input  [3:0]  dn;             // data-num  : 客人編號
    input  [TIME_W-1:0] dt;       // data-time : 服務時間

    //==================== 狀態輸出 ===========================
    output reg        busy;       // =1，櫃台忙碌
    output reg [3:0]  num;        // 現正服務之客人編號	(idle=0)
    output reg [TIME_W-1:0] rem;  // 倒數剩餘時間		(idle=0)

	//--------------------------------------------------------------
	//  主時序區塊
	//  -----------------------------------------------------------
	//  ld=1   : 載入資料並進入忙碌狀態 (busy<=1)
	//  busy=1 : 每拍 rem--；倒數至 0 釋放櫃台 (busy<=0)
	//--------------------------------------------------------------
	always @(posedge clk or negedge rst_n) begin
		if (!rst_n) begin
			// ---------- 非同步重設 --------------------------------
			busy <= 1'b0;
			num  <= 4'd0;
			rem  <= {TIME_W{1'b0}};
		end
		else begin
			if (ld) begin
				// ---------- 進入服務 -------------------------------
				busy <= 1'b1;
				num  <= dn;
				rem  <= dt;
			end
			else if (busy) begin
				// ---------- 服務進行中：倒數 -----------------------
				if (rem > 1)
					rem <= rem - 1'b1;          // 尚未完成
				else begin
					// rem==1 : 下一拍歸 0，釋放櫃台
					busy <= 1'b0;
					num  <= 4'd0;
					rem  <= {TIME_W{1'b0}};
				end
			end
			// idle 狀態 (busy=0 且 ld=0) : 保持輸出為 0
		end
	end
endmodule

dispatcher.v
//--------------------------------------------------------------
//  dispatcher.v
//  -----------------------------------------------------------
//  1. 功能 : 從佇列 FIFO 取出一筆資料，依序派發給
//            第一個「空閒」的櫃檯 (counter)。
//  2. 規則 : 固定優先權  櫃檯1 → 櫃檯2 → 櫃檯3
//            只要成功派發，就對 FIFO 送出 re=1 讀脈衝。
//  3. 時序 : 以 clk 正緣為基準，所有旗標皆同步重設。
//--------------------------------------------------------------
module dispatcher(clk, rst_n, empty, busy, qn, qt, re, ld1, ld2, ld3, dn1, dt1, dn2, dt2, dn3, dt3);
    //==================== 時脈 / 重設 =========================
    input  clk;
    input  rst_n;              // 同步低有效

    //==================== 來自 FIFO 的訊號 =====================
    input        empty;        // =1 代表 FIFO 為空
    input  [3:0] qn;           // 佇列首端客人編號
    input  [3:0] qt;           // 佇列首端服務時間

    //==================== 各櫃檯忙碌狀態 ======================
    // busy[i] = 1 → 該櫃檯正在服務，不可派發
    input  [2:0] busy;

    //==================== 給 FIFO 的控制 ======================
    output reg   re;           // 讀出脈衝 (HIGH 1 個 clk)

    //==================== 給三個 counter 的載入控制 ===========
    // ld?  : 載入脈衝 (HIGH 1 個 clk)
    // dn?/dt? : 欲載入之 {編號, 時間}
    output reg   ld1, ld2, ld3;
    output reg [3:0] dn1, dn2, dn3;
    output reg [3:0] dt1, dt2, dt3;

	//--------------------------------------------------------------
	//  派發邏輯
	//--------------------------------------------------------------
	always @(posedge clk or negedge rst_n) begin
		if (!rst_n) begin
			// --------- 非同步重設 ---------------------------------
			re  <= 1'b0;
			ld1 <= 1'b0;  dn1 <= 4'd0;  dt1 <= 4'd0;
			ld2 <= 1'b0;  dn2 <= 4'd0;  dt2 <= 4'd0;
			ld3 <= 1'b0;  dn3 <= 4'd0;  dt3 <= 4'd0;
		end
		else begin
			// --------- 預設值：每拍先清脈衝 ------------------------
			re  <= 1'b0;
			ld1 <= 1'b0;  ld2 <= 1'b0;  ld3 <= 1'b0;

			// --------- 當 FIFO 非空，嘗試派發 ----------------------
			if (!empty) begin
				// --- 優先檢查櫃檯1 ---------------------------------
				if (!busy[0]) begin
					re  <= 1'b1;        // 讀出 FIFO
					ld1 <= 1'b1;        // 觸發櫃檯1 載入
					dn1 <= qn;          // 資料送入櫃檯1
					dt1 <= qt;
				end
				// --- 再檢查櫃檯2 -----------------------------------
				else if (!busy[1]) begin
					re  <= 1'b1;
					ld2 <= 1'b1;
					dn2 <= qn;
					dt2 <= qt;
				end
				// --- 最後檢查櫃檯3 ---------------------------------
				else if (!busy[2]) begin
					re  <= 1'b1;
					ld3 <= 1'b1;
					dn3 <= qn;
					dt3 <= qt;
				end
				// 若全忙碌：不派發，re=0，資料留在 FIFO
			end
		end
	end
endmodule

queue.v
//--------------------------------------------------------------
//  queue.v  -  簡易參數化 FIFO（深度 DEPTH，預設 3）
//  - 用於暫存尚未被派發到櫃檯的客人資料
//  - 每筆資料包含 {客人編號 4-bit, 服務時間 4-bit}
//--------------------------------------------------------------
module queue(clk, rst_n, we, dn, dt, re, qn, qt, full, empty, qdbg);
    parameter DT_SZ = 4;					// 資料大小，預設 4 bits
    parameter DEPTH = 3;					// 佇列深度
    parameter PTR_W = 2;          			// PTR_W = (int)(log2(DEPTH))+1
	// DEPTH = 3 時，PTR_W 固定 2 bit

    input  clk;                          	// 系統時脈
    input  rst_n;                        	// 同步低有效重設

    // 寫入端 (enqueue)
    input         		we;                 // we=1 且 ~full 時寫入
    input  [DT_SZ-1:0]  dn;                 // data-num  : 客人編號
    input  [DT_SZ-1:0]  dt;                 // data-time : 服務時間
    
	// 讀出端 (dequeue)
    input         		re;                 // re=1 且 ~empty 時讀出
    output [DT_SZ-1:0]  qn;                 // queue-num  : 佇列首端客人編號
    output [DT_SZ-1:0]  qt;                 // queue-time : 佇列首端服務時間
    
	// 狀態旗標
    output full;                            // 佇列已滿
    output empty;                           // 佇列為空
    
	//--------------------------------------------------------------
	//  內部儲存結構
	//--------------------------------------------------------------
	reg [DT_SZ-1:0] nm [0:DEPTH-1];   // 編號暫存
	reg [DT_SZ-1:0] tm [0:DEPTH-1];   // 時間暫存

	reg [PTR_W-1:0] hd;   // head 讀指標
	reg [PTR_W-1:0] tl;   // tail 寫指標
	reg [PTR_W-1:0] ct;   // 佇列目前元素數 (0-DEPTH)

	//--------------------------------------------------------------
	//  即時輸出
	//--------------------------------------------------------------
	assign qn    = nm[hd];               // 讀指標指向的資料
	assign qt    = tm[hd];
	assign full  = (ct == DEPTH);        // 已填滿
	assign empty = (ct == 0);            // 沒有資料
	
	// for 迴圈用
	integer i;

	// 串接資料供波形觀察
    output reg [DEPTH*2*DT_SZ-1:0] qdbg;
    always @(hd or tl) begin
		qdbg = {DEPTH*2*DT_SZ{1'b0}};
        for(i = 0; i < ct; i = i + 1) begin
            qdbg = {qdbg, nm[(hd+i)%DEPTH], tm[(hd+i)%DEPTH]};
        end
		for(     ; i < DEPTH; i = i + 1) begin
            qdbg = {qdbg, 8'd0};
		end
    end

	//--------------------------------------------------------------
	//  寫入 / 讀出 控制邏輯
	//--------------------------------------------------------------
	always @(posedge clk or negedge rst_n) begin
		if (!rst_n) begin
			hd <= 0;
			tl <= 0;
			ct <= 0;
			for (i = 0; i < DEPTH; i = i + 1) begin
				nm[i] <= {DT_SZ{1'b0}};      // 編號清 0
				tm[i] <= {DT_SZ{1'b0}};      // 時間清 0
        	end
		end
		else begin
			// 寫入動作 ------------------------------------------------
			if (we && !full) begin
				nm[tl] <= dn;
				tm[tl] <= dt;
				tl <= (tl == DEPTH-1) ? 0 : tl + 1;   // 環形遞增
			end

			// 讀出動作 ------------------------------------------------
			if (re && !empty) begin
				hd <= (hd == DEPTH-1) ? 0 : hd + 1;   // 環形遞增
			end

			// 元素計數器 --------------------------------------------
			case ({we && !full, re && !empty})
				2'b10: ct <= ct + 1;   // 只有寫入
				2'b01: ct <= ct - 1;   // 只有讀出
				default: ;             // 其餘情況 ct 不變
			endcase
		end
	end
endmodule

top.v
//--------------------------------------------------------------
//  top.v  -  Queue / Dispatcher / Counter 整合測試平台
//           (針對 ISE Design Suite 14.7 產生)
//--------------------------------------------------------------
//  系統概要：
//  -----------------------------------------------------------
//  1. 來源：外部會以 in_valid=1 送入 {客人編號 in_num[3:0], 服務時間 in_time[3:0]}
//  2. 流程：
//      2-1. queue   : 尚無櫃檯可用時，資料先進 FIFO (深度=3)
//      2-2. dispatcher : 偵測空櫃檯，從 queue 取值派發 (固定優先權 櫃檯1->2->3)
//      2-3. counter : 櫃檯內部倒數；完成後自動 idle
//  3. 輸出：
//      num1/clk1 ... num3/clk3   : 各櫃檯現正服務客人編號 / 剩餘倒數
//      queue                     : FIFO 內容除錯觀察 (24-bit)
//--------------------------------------------------------------
module top(clk, rst_n, in_valid, in_num, in_time, num1, clk1, num2, clk2, num3, clk3, 
			qdbg, 
			fifo_re, ld1, ld2, ld3, busy, fifo_full, fifo_emp, fifo_num, fifo_tim, 
			dn1, dn2, dn3, dt1, dt2, dt3); // debug
    //==================== 時脈 / 重設 =========================
    input  clk;                   // 20 ns 週期 (50 MHz)
    input  rst_n;                 // 同步低有效

    //==================== 來源輸入 ============================
    input         in_valid;       // =1 時 in_num / in_time 有效
    input  [3:0]  in_num;         // 客人編號 (0 為空)
    input  [3:0]  in_time;        // 服務時間 (1~7)

    //==================== 櫃檯狀態輸出 ========================
    output [3:0]  num1;           // 櫃檯1 現正服務客人
    output [3:0]  clk1;           // 櫃檯1 剩餘時間
    output [3:0]  num2;
    output [3:0]  clk2;
    output [3:0]  num3;
    output [3:0]  clk3;

    //==================== FIFO 佇列除錯用 ====================
	// 除錯觀察用
    output [23:0] qdbg;

	//--------------------------------------------------------------
	//  內部線路宣告
	//--------------------------------------------------------------
	output        fifo_re;              // dispatcher 對 FIFO 的讀脈衝
	output        ld1, ld2, ld3;        // dispatcher -> counter 的載入
	output [2:0]  busy;                 // counters 忙碌旗標
	output        fifo_full, fifo_emp;  // FIFO 滿 / 空
	output [3:0]  fifo_num;             // queue 輸出編號
	output [3:0]  fifo_tim;             // queue 輸出時間
	output [3:0]  dn1, dn2, dn3;        // 發送至 counter 的編號
	output [3:0]  dt1, dt2, dt3;        // 發送至 counter 的時間

	//--------------------------------------------------------------
	//  模組例化
	//--------------------------------------------------------------
	//  1. 佇列 FIFO ---------------------------------------------
	// in_valid = 1，上層總是嘗試寫入，queue 內部會判斷 full
	// 深度固定為 3 (可參數化)
	queue #(3) u_queue (
		clk, rst_n, in_valid, in_num, in_time, 
		fifo_re, fifo_num, fifo_tim, fifo_full, fifo_emp, 
		qdbg); // debug

	//  2. 調度器 Dispatcher -------------------------------------
	// busy = {b3,b2,b1}
	dispatcher u_disp (
		clk, rst_n, fifo_emp, busy, fifo_num, fifo_tim, fifo_re, 
		ld1, ld2, ld3, dn1, dt1, dn2, dt2, dn3, dt3);

	//  3. 三個櫃檯 Counter --------------------------------------
	//      counter#1
	counter u_c1 (clk, rst_n, ld1, dn1, dt1, busy[0], num1, clk1);
	//      counter#2
	counter u_c2 (clk, rst_n, ld2, dn2, dt2, busy[1], num2, clk2);
	//      counter#3
	counter u_c3 (clk, rst_n, ld3, dn3, dt3, busy[2], num3, clk3);
endmodule

top_tb.v
`timescale 1ns / 1ps
module top_tb;

	// Inputs
	reg clk;
	reg rst_n;
	reg in_valid;
	reg [3:0] in_num;
	reg [3:0] in_time;

	// Outputs
	wire [3:0] num1;
	wire [3:0] clk1;
	wire [3:0] num2;
	wire [3:0] clk2;
	wire [3:0] num3;
	wire [3:0] clk3;
	wire [23:0] qdbg;
	wire fifo_re;
	wire ld1;
	wire ld2;
	wire ld3;
	wire [2:0] busy;
	wire fifo_full;
	wire fifo_emp;
	wire [3:0] fifo_num;
	wire [3:0] fifo_tim;
	wire [3:0] dn1;
	wire [3:0] dt1;
	wire [3:0] dn2;
	wire [3:0] dt2;
	wire [3:0] dn3;
	wire [3:0] dt3;

	
	// Instantiate the Unit Under Test (UUT)
	top uut (
		.clk(clk), 
		.rst_n(rst_n), 
		.in_valid(in_valid), 
		.in_num(in_num), 
		.in_time(in_time), 
		.num1(num1), 
		.clk1(clk1), 
		.num2(num2), 
		.clk2(clk2), 
		.num3(num3), 
		.clk3(clk3), 
		.qdbg(qdbg), 
		.fifo_re(fifo_re), 
		.ld1(ld1), 
		.ld2(ld2), 
		.ld3(ld3), 
		.busy(busy), 
		.fifo_full(fifo_full), 
		.fifo_emp(fifo_emp), 
		.fifo_num(fifo_num), 
		.fifo_tim(fifo_tim), 
		.dn1(dn1), 
		.dt1(dt1), 
		.dn2(dn2), 
		.dt2(dt2), 
		.dn3(dn3), 
		.dt3(dt3)
	);

//==== Clock : 20 ns 週期 ======================================
always #10 clk = ~clk;

//==== Reset ===================================================
initial begin
    clk = 0;
    rst_n = 0;
    in_valid = 0;
    in_num = 0;
    in_time = 0;
    #35 rst_n = 1;           // 釋放重設
end

//==== 送客人 Task =============================================
task send_cust;
    input [7:0] num;
    input [2:0] tim;
begin
    @(negedge clk);
    in_valid = 1;
    in_num   = num;
    in_time  = tim;
    @(negedge clk);
    in_valid = 0;
    in_num   = 0;
    in_time  = 0;
end
endtask

//==== Stimulus ================================================
initial begin
    @(posedge rst_n);        // 等待重設結束
    #20;

    // ── 先填滿三個櫃台 ───────────────────────────────
    send_cust(4'd1, 4'd3);
    send_cust(4'd2, 4'd2);
    send_cust(4'd3, 4'd4);

    // ── 再塞進 FIFO（深度 3）────────────────────────
    send_cust(4'd4, 4'd1);
    send_cust(4'd5, 4'd5);
    send_cust(4'd6, 4'd2);

    // ── 佇列已滿，以下客人應被丟棄 ──────────────────
    send_cust(4'd7, 4'd3);

    // ── 等待部分櫃台釋放，再送新客人 ────────────────
    #500;
    send_cust(4'd8, 4'd2);
    send_cust(4'd9, 4'd6);

    // ── 結束模擬 ───────────────────────────────────
    #1000 $finish;
end

//==== 波形輸出 (VCD) ==========================================
initial begin
    $dumpfile("top_tb.vcd");
    $dumpvars(0, top_tb);
end

endmodule

top_tb.vcd
$date
   Thu May 29 21:06:05 2025
$end
$version
  P.20131013
$end
$timescale
  1ps
$end
$scope module top_tb $end
$var wire 1 .! num1 [3] $end
$var wire 1 /! num1 [2] $end
$var wire 1 0! num1 [1] $end
$var wire 1 1! num1 [0] $end
$var wire 1 2! clk1 [3] $end
$var wire 1 3! clk1 [2] $end
$var wire 1 4! clk1 [1] $end
$var wire 1 5! clk1 [0] $end
$var wire 1 6! num2 [3] $end
$var wire 1 7! num2 [2] $end
$var wire 1 8! num2 [1] $end
$var wire 1 9! num2 [0] $end
$var wire 1 :! clk2 [3] $end
$var wire 1 ;! clk2 [2] $end
$var wire 1 <! clk2 [1] $end
$var wire 1 =! clk2 [0] $end
$var wire 1 >! num3 [3] $end
$var wire 1 ?! num3 [2] $end
$var wire 1 @! num3 [1] $end
$var wire 1 A! num3 [0] $end
$var wire 1 B! clk3 [3] $end
$var wire 1 C! clk3 [2] $end
$var wire 1 D! clk3 [1] $end
$var wire 1 E! clk3 [0] $end
$var wire 1 ?" qdbg [23] $end
$var wire 1 @" qdbg [22] $end
$var wire 1 A" qdbg [21] $end
$var wire 1 B" qdbg [20] $end
$var wire 1 C" qdbg [19] $end
$var wire 1 D" qdbg [18] $end
$var wire 1 E" qdbg [17] $end
$var wire 1 F" qdbg [16] $end
$var wire 1 G" qdbg [15] $end
$var wire 1 H" qdbg [14] $end
$var wire 1 I" qdbg [13] $end
$var wire 1 J" qdbg [12] $end
$var wire 1 K" qdbg [11] $end
$var wire 1 L" qdbg [10] $end
$var wire 1 M" qdbg [9] $end
$var wire 1 N" qdbg [8] $end
$var wire 1 O" qdbg [7] $end
$var wire 1 P" qdbg [6] $end
$var wire 1 Q" qdbg [5] $end
$var wire 1 R" qdbg [4] $end
$var wire 1 S" qdbg [3] $end
$var wire 1 T" qdbg [2] $end
$var wire 1 U" qdbg [1] $end
$var wire 1 V" qdbg [0] $end
$var wire 1 4" fifo_re $end
$var wire 1 w" ld1 $end
$var wire 1 '# ld2 $end
$var wire 1 5# ld3 $end
$var wire 1 h" busy [2] $end
$var wire 1 i" busy [1] $end
$var wire 1 j" busy [0] $end
$var wire 1 =" fifo_full $end
$var wire 1 _" fifo_emp $end
$var wire 1 `" fifo_num [3] $end
$var wire 1 a" fifo_num [2] $end
$var wire 1 b" fifo_num [1] $end
$var wire 1 c" fifo_num [0] $end
$var wire 1 d" fifo_tim [3] $end
$var wire 1 e" fifo_tim [2] $end
$var wire 1 f" fifo_tim [1] $end
$var wire 1 g" fifo_tim [0] $end
$var wire 1 x" dn1 [3] $end
$var wire 1 y" dn1 [2] $end
$var wire 1 z" dn1 [1] $end
$var wire 1 {" dn1 [0] $end
$var wire 1 |" dt1 [3] $end
$var wire 1 }" dt1 [2] $end
$var wire 1 ~" dt1 [1] $end
$var wire 1 !# dt1 [0] $end
$var wire 1 (# dn2 [3] $end
$var wire 1 )# dn2 [2] $end
$var wire 1 *# dn2 [1] $end
$var wire 1 +# dn2 [0] $end
$var wire 1 ,# dt2 [3] $end
$var wire 1 -# dt2 [2] $end
$var wire 1 .# dt2 [1] $end
$var wire 1 /# dt2 [0] $end
$var wire 1 6# dn3 [3] $end
$var wire 1 7# dn3 [2] $end
$var wire 1 8# dn3 [1] $end
$var wire 1 9# dn3 [0] $end
$var wire 1 :# dt3 [3] $end
$var wire 1 ;# dt3 [2] $end
$var wire 1 <# dt3 [1] $end
$var wire 1 =# dt3 [0] $end
$var reg 1 z clk $end
$var reg 1 { rst_n $end
$var reg 1 | in_valid $end
$var reg 4 } in_num [3:0] $end
$var reg 4 ~ in_time [3:0] $end
$scope task send_cust $end
$var reg 8 !! num [7:0] $end
$var reg 3 "! tim [2:0] $end
$upscope $end
$scope module uut $end
$var wire 1 3# clk $end
$var wire 1 4# rst_n $end
$var wire 1 +" in_valid $end
$var wire 1 ," in_num [3] $end
$var wire 1 -" in_num [2] $end
$var wire 1 ." in_num [1] $end
$var wire 1 /" in_num [0] $end
$var wire 1 0" in_time [3] $end
$var wire 1 1" in_time [2] $end
$var wire 1 2" in_time [1] $end
$var wire 1 3" in_time [0] $end
$var wire 1 .! num1 [3] $end
$var wire 1 /! num1 [2] $end
$var wire 1 0! num1 [1] $end
$var wire 1 1! num1 [0] $end
$var wire 1 2! clk1 [3] $end
$var wire 1 3! clk1 [2] $end
$var wire 1 4! clk1 [1] $end
$var wire 1 5! clk1 [0] $end
$var wire 1 6! num2 [3] $end
$var wire 1 7! num2 [2] $end
$var wire 1 8! num2 [1] $end
$var wire 1 9! num2 [0] $end
$var wire 1 :! clk2 [3] $end
$var wire 1 ;! clk2 [2] $end
$var wire 1 <! clk2 [1] $end
$var wire 1 =! clk2 [0] $end
$var wire 1 >! num3 [3] $end
$var wire 1 ?! num3 [2] $end
$var wire 1 @! num3 [1] $end
$var wire 1 A! num3 [0] $end
$var wire 1 B! clk3 [3] $end
$var wire 1 C! clk3 [2] $end
$var wire 1 D! clk3 [1] $end
$var wire 1 E! clk3 [0] $end
$var wire 1 ?" qdbg [23] $end
$var wire 1 @" qdbg [22] $end
$var wire 1 A" qdbg [21] $end
$var wire 1 B" qdbg [20] $end
$var wire 1 C" qdbg [19] $end
$var wire 1 D" qdbg [18] $end
$var wire 1 E" qdbg [17] $end
$var wire 1 F" qdbg [16] $end
$var wire 1 G" qdbg [15] $end
$var wire 1 H" qdbg [14] $end
$var wire 1 I" qdbg [13] $end
$var wire 1 J" qdbg [12] $end
$var wire 1 K" qdbg [11] $end
$var wire 1 L" qdbg [10] $end
$var wire 1 M" qdbg [9] $end
$var wire 1 N" qdbg [8] $end
$var wire 1 O" qdbg [7] $end
$var wire 1 P" qdbg [6] $end
$var wire 1 Q" qdbg [5] $end
$var wire 1 R" qdbg [4] $end
$var wire 1 S" qdbg [3] $end
$var wire 1 T" qdbg [2] $end
$var wire 1 U" qdbg [1] $end
$var wire 1 V" qdbg [0] $end
$var wire 1 4" fifo_re $end
$var wire 1 w" ld1 $end
$var wire 1 '# ld2 $end
$var wire 1 5# ld3 $end
$var wire 1 h" busy [2] $end
$var wire 1 i" busy [1] $end
$var wire 1 j" busy [0] $end
$var wire 1 =" fifo_full $end
$var wire 1 _" fifo_emp $end
$var wire 1 `" fifo_num [3] $end
$var wire 1 a" fifo_num [2] $end
$var wire 1 b" fifo_num [1] $end
$var wire 1 c" fifo_num [0] $end
$var wire 1 d" fifo_tim [3] $end
$var wire 1 e" fifo_tim [2] $end
$var wire 1 f" fifo_tim [1] $end
$var wire 1 g" fifo_tim [0] $end
$var wire 1 x" dn1 [3] $end
$var wire 1 y" dn1 [2] $end
$var wire 1 z" dn1 [1] $end
$var wire 1 {" dn1 [0] $end
$var wire 1 (# dn2 [3] $end
$var wire 1 )# dn2 [2] $end
$var wire 1 *# dn2 [1] $end
$var wire 1 +# dn2 [0] $end
$var wire 1 6# dn3 [3] $end
$var wire 1 7# dn3 [2] $end
$var wire 1 8# dn3 [1] $end
$var wire 1 9# dn3 [0] $end
$var wire 1 |" dt1 [3] $end
$var wire 1 }" dt1 [2] $end
$var wire 1 ~" dt1 [1] $end
$var wire 1 !# dt1 [0] $end
$var wire 1 ,# dt2 [3] $end
$var wire 1 -# dt2 [2] $end
$var wire 1 .# dt2 [1] $end
$var wire 1 /# dt2 [0] $end
$var wire 1 :# dt3 [3] $end
$var wire 1 ;# dt3 [2] $end
$var wire 1 <# dt3 [1] $end
$var wire 1 =# dt3 [0] $end
$scope module u_queue $end
$var wire 1 3# clk $end
$var wire 1 4# rst_n $end
$var wire 1 +" we $end
$var wire 1 ," dn [3] $end
$var wire 1 -" dn [2] $end
$var wire 1 ." dn [1] $end
$var wire 1 /" dn [0] $end
$var wire 1 0" dt [3] $end
$var wire 1 1" dt [2] $end
$var wire 1 2" dt [1] $end
$var wire 1 3" dt [0] $end
$var wire 1 4" re $end
$var wire 1 `" qn [3] $end
$var wire 1 a" qn [2] $end
$var wire 1 b" qn [1] $end
$var wire 1 c" qn [0] $end
$var wire 1 d" qt [3] $end
$var wire 1 e" qt [2] $end
$var wire 1 f" qt [1] $end
$var wire 1 g" qt [0] $end
$var wire 1 =" full $end
$var wire 1 _" empty $end
$var wire 1 ?" qdbg [23] $end
$var wire 1 @" qdbg [22] $end
$var wire 1 A" qdbg [21] $end
$var wire 1 B" qdbg [20] $end
$var wire 1 C" qdbg [19] $end
$var wire 1 D" qdbg [18] $end
$var wire 1 E" qdbg [17] $end
$var wire 1 F" qdbg [16] $end
$var wire 1 G" qdbg [15] $end
$var wire 1 H" qdbg [14] $end
$var wire 1 I" qdbg [13] $end
$var wire 1 J" qdbg [12] $end
$var wire 1 K" qdbg [11] $end
$var wire 1 L" qdbg [10] $end
$var wire 1 M" qdbg [9] $end
$var wire 1 N" qdbg [8] $end
$var wire 1 O" qdbg [7] $end
$var wire 1 P" qdbg [6] $end
$var wire 1 Q" qdbg [5] $end
$var wire 1 R" qdbg [4] $end
$var wire 1 S" qdbg [3] $end
$var wire 1 T" qdbg [2] $end
$var wire 1 U" qdbg [1] $end
$var wire 1 V" qdbg [0] $end
$var reg 12 W" nm [3:0] $end
$var reg 12 X" tm [3:0] $end
$var reg 2 Y" hd [1:0] $end
$var reg 2 Z" tl [1:0] $end
$var reg 2 [" ct [1:0] $end
$var integer 32 \" i $end
$upscope $end
$scope module u_disp $end
$var wire 1 3# clk $end
$var wire 1 4# rst_n $end
$var wire 1 _" empty $end
$var wire 1 `" qn [3] $end
$var wire 1 a" qn [2] $end
$var wire 1 b" qn [1] $end
$var wire 1 c" qn [0] $end
$var wire 1 d" qt [3] $end
$var wire 1 e" qt [2] $end
$var wire 1 f" qt [1] $end
$var wire 1 g" qt [0] $end
$var wire 1 h" busy [2] $end
$var wire 1 i" busy [1] $end
$var wire 1 j" busy [0] $end
$var reg 1 k" re $end
$var reg 1 l" ld1 $end
$var reg 1 m" ld2 $end
$var reg 1 n" ld3 $end
$var reg 4 o" dn1 [3:0] $end
$var reg 4 p" dn2 [3:0] $end
$var reg 4 q" dn3 [3:0] $end
$var reg 4 r" dt1 [3:0] $end
$var reg 4 s" dt2 [3:0] $end
$var reg 4 t" dt3 [3:0] $end
$upscope $end
$scope module u_c1 $end
$var wire 1 3# clk $end
$var wire 1 4# rst_n $end
$var wire 1 w" ld $end
$var wire 1 x" dn [3] $end
$var wire 1 y" dn [2] $end
$var wire 1 z" dn [1] $end
$var wire 1 {" dn [0] $end
$var wire 1 |" dt [3] $end
$var wire 1 }" dt [2] $end
$var wire 1 ~" dt [1] $end
$var wire 1 !# dt [0] $end
$var reg 1 "# busy $end
$var reg 4 ## num [3:0] $end
$var reg 4 $# rem [3:0] $end
$upscope $end
$scope module u_c2 $end
$var wire 1 3# clk $end
$var wire 1 4# rst_n $end
$var wire 1 '# ld $end
$var wire 1 (# dn [3] $end
$var wire 1 )# dn [2] $end
$var wire 1 *# dn [1] $end
$var wire 1 +# dn [0] $end
$var wire 1 ,# dt [3] $end
$var wire 1 -# dt [2] $end
$var wire 1 .# dt [1] $end
$var wire 1 /# dt [0] $end
$var reg 1 0# busy $end
$var reg 4 1# num [3:0] $end
$var reg 4 2# rem [3:0] $end
$upscope $end
$scope module u_c3 $end
$var wire 1 3# clk $end
$var wire 1 4# rst_n $end
$var wire 1 5# ld $end
$var wire 1 6# dn [3] $end
$var wire 1 7# dn [2] $end
$var wire 1 8# dn [1] $end
$var wire 1 9# dn [0] $end
$var wire 1 :# dt [3] $end
$var wire 1 ;# dt [2] $end
$var wire 1 <# dt [1] $end
$var wire 1 =# dt [0] $end
$var reg 1 ># busy $end
$var reg 4 ?# num [3:0] $end
$var reg 4 @# rem [3:0] $end
$upscope $end
$upscope $end
$upscope $end
$enddefinitions $end
#0
$dumpvars
05!
00!
01!
0/!
0.!
0z
0{
0|
b0 }
b0 ~
bx !!
bx "!
04!
03!
02!
09!
08!
0E!
0S"
0D!
0?!
0U"
0Q"
0R"
0>!
0C!
0A!
0@!
0V"
0T"
0B!
0;!
0P"
0:!
0K"
0J"
0F"
0D"
0B"
0H"
0C"
0?"
0w"
0A"
05#
0h"
0'#
0="
0c"
1_"
0I"
0b"
0a"
0`"
0@"
0f"
0e"
0d"
04"
0{"
0G"
0j"
0i"
0N"
0L"
0g"
0z"
0M"
0E"
0O"
07!
06!
0=!
0<!
0*#
03#
0(#
0-#
09#
0:#
0!#
0+#
0)#
0.#
08#
07#
0<#
0,#
0=#
0y"
0}"
0;#
0/#
06#
0x"
0~"
0|"
b0 W"
b0 X"
b0 Y"
b0 Z"
b0 ["
b11 \"
0k"
0l"
0m"
0n"
b0 o"
b0 p"
b0 q"
b0 r"
b0 s"
b0 t"
0"#
b0 ##
b0 $#
00#
b0 1#
b0 2#
0>#
b0 ?#
b0 @#
0,"
04#
0-"
01"
00"
0/"
0."
02"
03"
0+"
$end
#10000
1z
13#
b11 \"
#20000
0z
03#
#30000
1z
13#
b11 \"
#35000
1{
14#
#40000
0z
03#
#50000
1z
13#
#55000
b1 !!
b11 "!
#60000
0z
1|
b1 }
b11 ~
03#
1/"
12"
13"
1+"
#70000
1z
1F"
1B"
1c"
0_"
1f"
1g"
1E"
13#
b100000000 W"
b1100000000 X"
b1 Z"
b1 ["
#80000
0z
0|
b0 }
b0 ~
b10 !!
b10 "!
03#
0/"
02"
03"
0+"
#90000
1z
1w"
14"
1{"
13#
1!#
1~"
1k"
1l"
b1 o"
b11 r"
#100000
0z
1|
b10 }
b10 ~
03#
1."
12"
1+"
#110000
15!
11!
1z
14!
0c"
1I"
1b"
1j"
0g"
1M"
13#
b100100000 W"
b1100100000 X"
b1 Y"
b10 Z"
1k"
1l"
1"#
b1 ##
b11 $#
#120000
0z
0|
b0 }
b0 ~
b11 !!
b100 "!
03#
0."
02"
0+"
#130000
1z
0w"
1'#
1_"
0b"
0f"
1*#
13#
1.#
b10 Y"
b0 ["
1k"
0l"
1m"
b10 p"
b10 s"
#140000
0z
1|
b11 }
b100 ~
03#
11"
1/"
1."
1+"
#150000
05!
1z
18!
1Q"
1R"
1T"
0'#
1c"
0_"
1b"
1e"
04"
1i"
1<!
13#
b100100011 W"
b1100100100 X"
b0 Z"
b1 ["
0k"
0m"
b10 $#
10#
b10 1#
b10 2#
#160000
0z
0|
b0 }
b0 ~
b100 !!
b1 "!
03#
01"
0/"
0."
0+"
#170000
15!
1z
04!
15#
14"
1=!
0<!
13#
19#
18#
1;#
1k"
1n"
b11 q"
b100 t"
b1 $#
b1 2#
#180000
0z
1|
b100 }
b1 ~
03#
1-"
13"
1+"
#190000
05!
01!
1z
08!
1C!
1A!
1@!
0B"
1h"
0c"
0b"
1a"
1@"
0e"
0j"
0i"
1g"
0E"
0=!
13#
b10000100011 W"
b100100100 X"
b0 Y"
b1 Z"
1k"
1n"
0"#
b0 ##
b0 $#
00#
b0 1#
b0 2#
1>#
b11 ?#
b100 @#
#200000
0z
0|
b0 }
b0 ~
b101 !!
b101 "!
03#
0-"
03"
0+"
#210000
1z
1w"
05#
1_"
1b"
0a"
1f"
0{"
0g"
13#
1y"
0~"
b1 Y"
b0 ["
1k"
1l"
0n"
b100 o"
b1 r"
#220000
0z
1|
b101 }
b101 ~
03#
1-"
11"
1/"
13"
1+"
#230000
15!
1/!
1z
1E!
1D!
0C!
1J"
1H"
0w"
1c"
0_"
0I"
0b"
1a"
0f"
1e"
04"
1j"
1N"
1L"
1g"
0M"
13#
b10001010011 W"
b101010100 X"
b10 Z"
b1 ["
0k"
0l"
1"#
b100 ##
b1 $#
b11 @#
#240000
0z
0|
b0 }
b0 ~
b110 !!
b10 "!
03#
0-"
01"
0/"
03"
0+"
