counter.v
//--------------------------------------------------------------
//  counter.v
//  -----------------------------------------------------------
//  功能 : 單一櫃台（Counter）之服務狀態機
//         ─ 收到 1-拍脈衝 ld=1 時，載入 {客人編號 dn, 服務時間 dt}
//         ─ busy=1 代表櫃台正在服務；rem 每拍倒數
//         ─ rem 歸零後自動釋放櫃台 (busy<=0) 並將輸出歸 0
//--------------------------------------------------------------
module counter(clk, rst_n, ld, dn, dt, busy, num, rem);
    parameter DT_SZ = 4;					// 資料大小，預設 4 bits

    //==================== 時脈 / 重設 =========================
    input  clk;                   // 系統時脈
    input  rst_n;                 // 同步低有效重設

    //==================== 新客人載入介面 ======================
    input         ld;             // 載入脈衝 (HIGH 1 拍)
    input  [DT_SZ-1:0] dn;             // data-num  : 客人編號
    input  [DT_SZ-1:0] dt;       // data-time : 服務時間

    //==================== 狀態輸出 ===========================
    output reg        busy;      // =1，櫃台忙碌
    output reg [DT_SZ-1:0] num;	 // 現正服務之客人編號	(idle=0)
    output reg [DT_SZ-1:0] rem;  // 倒數剩餘時間		(idle=0)

	//--------------------------------------------------------------
	//  主時序區塊
	//  -----------------------------------------------------------
	//  ld=1   : 載入資料並進入忙碌狀態 (busy<=1)
	//  busy=1 : 每拍 rem--；倒數至 0 釋放櫃台 (busy<=0)
	//--------------------------------------------------------------
	always @(posedge clk or negedge rst_n) begin
		if (!rst_n) begin
			// ---------- 非同步重設 --------------------------------
			busy <= 1'b0;
			num  <= {DT_SZ{1'b0}};
			rem  <= {DT_SZ{1'b0}};
		end
		else begin
			if (ld) begin
				// ---------- 進入服務 -------------------------------
				busy <= 1'b1;
				num  <= dn;
				rem  <= dt;
			end
			else if (busy) begin
				// ---------- 服務進行中：倒數 -----------------------
				if (rem > 1)
					rem <= rem - 1'b1;          // 尚未完成
				else begin
					// rem==1 : 下一拍歸 0，釋放櫃台
					busy <= 1'b0;
					num  <= {DT_SZ{1'b0}};
					rem  <= {DT_SZ{1'b0}};
				end
			end
			// idle 狀態 (busy=0 且 ld=0) : 保持輸出為 0
		end
	end
endmodule

counter_tb.v
`timescale 1ns/1ps
module counter_tb;
// ==== DUT 連接埠 ====
reg  clk, rst_n;
reg  ld;
reg  [3:0] dn;
reg  [3:0] dt;

wire busy;
wire [3:0] num;
wire [3:0] rem;

// ==== DUT 例化 ====
counter #(.DT_SZ(4)) dut (
    .clk(clk), .rst_n(rst_n),
    .ld(ld), .dn(dn), .dt(dt),
    .busy(busy), .num(num), .rem(rem)
);

// ==== Clock ====
always #10 clk = ~clk;

// ==== Reset ====
initial begin
    clk = 0; rst_n = 0;
    ld = 0; dn = 0; dt = 0;
    #35 rst_n = 1;
end

// ==== Stimulus ====
initial begin
    @(posedge rst_n);

    // 載入第一位客人 (3 拍)
    load_cust(4'd1,4'd3);
    // 等待櫃檯釋放
    wait(!busy);

    // 載入第二位客人 (6 拍)
    load_cust(4'd2,4'd6);
    wait(!busy);

    #100 $finish;
end

task load_cust(
    input [3:0] num, input [3:0] tim
);
begin
    @(negedge clk);
    ld = 1; dn = num; dt = tim;
    @(negedge clk);
    ld = 0; dn = 0; dt = 0;
end
endtask

// ==== VCD ====
initial begin
    $dumpfile("counter_tb.vcd");
    $dumpvars(0, counter_tb);
end
endmodule

data/counter_tb.vcd
$date
   Sat May 31 14:17:24 2025
$end
$version
  P.20131013
$end
$timescale
  1ps
$end
$scope module counter_tb $end
$var wire 1 ! busy $end
$var wire 1 " num [3] $end
$var wire 1 # num [2] $end
$var wire 1 $ num [1] $end
$var wire 1 % num [0] $end
$var wire 1 & rem [3] $end
$var wire 1 ' rem [2] $end
$var wire 1 ( rem [1] $end
$var wire 1 ) rem [0] $end
$var reg 1 * clk $end
$var reg 1 + rst_n $end
$var reg 1 , ld $end
$var reg 4 - dn [3:0] $end
$var reg 4 . dt [3:0] $end
$scope task load_cust $end
$var reg 4 / num [3:0] $end
$var reg 4 0 tim [3:0] $end
$upscope $end
$scope module dut $end
$var wire 1 1 clk $end
$var wire 1 2 rst_n $end
$var wire 1 3 ld $end
$var wire 1 4 dn [3] $end
$var wire 1 5 dn [2] $end
$var wire 1 6 dn [1] $end
$var wire 1 7 dn [0] $end
$var wire 1 8 dt [3] $end
$var wire 1 9 dt [2] $end
$var wire 1 : dt [1] $end
$var wire 1 ; dt [0] $end
$var reg 1 < busy $end
$var reg 4 = num [3:0] $end
$var reg 4 > rem [3:0] $end
$upscope $end
$upscope $end
$enddefinitions $end
#0
$dumpvars
0*
0+
0,
b0 -
b0 .
bx /
bx 0
0$
0#
0"
0)
0(
0'
0&
0!
0%
0<
b0 =
b0 >
05
03
04
0;
07
01
02
0:
06
09
08
$end
#10000
1*
11
#20000
0*
01
#30000
1*
11
#35000
1+
b1 /
b11 0
12
#40000
0*
1,
b1 -
b11 .
13
1;
17
01
1:
#50000
1*
1)
1(
1!
1%
1<
b1 =
b11 >
11
#60000
0*
0,
b0 -
b0 .
03
0;
07
01
0:
#70000
1*
0)
b10 >
11
#80000
0*
01
#90000
1*
1)
0(
b1 >
11
#100000
0*
01
#110000
1*
b10 /
b110 0
0)
0!
0%
0<
b0 =
b0 >
11
#120000
0*
1,
b10 -
b110 .
13
01
1:
16
19
#130000
1*
1$
1(
1'
1!
1<
b10 =
b110 >
11
#140000
0*
0,
b0 -
b0 .
03
01
0:
06
09
#150000
1*
1)
0(
b101 >
11
#160000
0*
01
#170000
1*
0)
b100 >
11
#180000
0*
01
#190000
1*
1)
1(
0'
b11 >
11
#200000
0*
01
#210000
1*
0)
b10 >
11
#220000
0*
01
#230000
1*
1)
0(
b1 >
11
#240000
0*
01
#250000
1*
0$
0)
0!
0<
b0 =
b0 >
11
