dispatcher.v
//--------------------------------------------------------------
//  dispatcher.v
//  -----------------------------------------------------------
//  1. 功能 : 從佇列 FIFO 取出一筆資料，依序派發給
//            第一個「空閒」的櫃檯 (counter)。
//  2. 規則 : 固定優先權  櫃檯1 → 櫃檯2 → 櫃檯3
//            只要成功派發，就對 FIFO 送出 re=1 讀脈衝。
//  3. 時序 : 以 clk 正緣為基準，所有旗標皆同步重設。
//--------------------------------------------------------------
module dispatcher(clk, rst_n, empty, busy, qn, qt, re, ld, dn, dt);
    parameter DT_SZ = 4;					// 資料大小，預設 4 bits
    parameter CNTER = 3;					// 櫃台數量
	//==================== 時脈 / 重設 =========================
    input  clk;
    input  rst_n;              // 同步低有效

    //==================== 來自 FIFO 的訊號 =====================
    input        empty;        // =1 代表 FIFO 為空
    input  [DT_SZ-1:0] qn;           // 佇列首端客人編號
    input  [DT_SZ-1:0] qt;           // 佇列首端服務時間

    //==================== 各櫃檯忙碌狀態 ======================
    // busy[i] = 1 → 該櫃檯正在服務，不可派發
    input  [CNTER-1:0] busy;

    //==================== 給 FIFO 的控制 ======================
    output reg   re;           // 讀出脈衝 (HIGH 1 個 clk)

    //==================== 給三個 counter 的載入控制 ===========
    // ld?  : 載入脈衝 (HIGH 1 個 clk)
    // dn?/dt? : 欲載入之 {編號, 時間}
    output reg [CNTER-1:0] ld;
	output reg [CNTER*DT_SZ-1:0] dn;
	output reg [CNTER*DT_SZ-1:0] dt;

	// for 迴圈用
	integer i;

	//--------------------------------------------------------------
	//  派發邏輯
	//--------------------------------------------------------------
	always @(posedge clk or negedge rst_n) begin
		if (!rst_n) begin
			// --------- 非同步重設 ---------------------------------
			re  <= 1'b0;
			ld <= {CNTER{1'b0}};       // 脈衝清 0
			dn <= {CNTER*DT_SZ{1'b0}}; // 暫存清 0
		end
		else begin
			#2
			// --------- 預設值：每拍先清脈衝 ----------------------------
			re  <= 1'b0;
			ld <= {CNTER{1'b0}};      // 脈衝清 0
			// --------- 當 FIFO 非空，嘗試派發 ----------------------
			if (!empty) begin
				for (i = 0; i < CNTER; i = i + 1) begin
					if (!busy[i] & !re) begin: uF
						re <= 1'b1; // 找到空位就標記退出 for 迴圈
						ld[i] <= 1'b1;
						dn[i*4+3:i*4] <= qn;
						dt[i*4+3:i*4] <= qt;
					end
				end
			end
			// if (!empty) begin
			// 	// --- 優先檢查櫃檯1 ---------------------------------
			// 	if (!busy[0]) begin
			// 		re  <= 1'b1;        // 讀出 FIFO
			// 		ld[0] <= 1'b1;        // 觸發櫃檯1 載入
			// 		dn[3:0] <= qn;          // 資料送入櫃檯1
			// 		dt[3:0] <= qt;
			// 	end
			// 	// --- 再檢查櫃檯2 -----------------------------------
			// 	else if (!busy[1]) begin
			// 		re  <= 1'b1;
			// 		ld[1] <= 1'b1;
			// 		dn[7:4] <= qn;
			// 		dt[7:4] <= qt;
			// 	end
			// 	// --- 最後檢查櫃檯3 ---------------------------------
			// 	else if (!busy[2]) begin
			// 		re  <= 1'b1;
			// 		ld[2] <= 1'b1;
			// 		dn[11:8] <= qn;
			// 		dt[11:8] <= qt;
			// 	end
			// 	// 若全忙碌：不派發，re=0，資料留在 FIFO
			// end
		end
	end
endmodule

dispatcher_tb.v
`timescale 1ns/1ps
module dispatcher_tb;
// ==== DUT 連接埠 ====
reg  clk, rst_n;
reg  empty;
reg  [3:0] qn;
reg  [3:0] qt;
reg  [2:0] busy;

wire re;
wire [2:0] ld;
wire [11:0] dn;
wire [11:0] dt;

// ==== DUT 例化 ====
dispatcher #(.DT_SZ(4), .CNTER(3)) dut (
    .clk(clk), .rst_n(rst_n),
    .empty(empty), .qn(qn), .qt(qt),
    .busy(busy),
    .re(re),
    .ld(ld),
    .dn(dn),
    .dt(dt)
);

// ==== Clock ====
always #10 clk = ~clk;

// ==== Reset ====
initial begin
    clk = 0; rst_n = 0;
    empty = 1; qn = 0; qt = 0; busy = 3'b111;
    #35 rst_n = 1;
end

// ==== Stimulus ====
initial begin
    @(posedge rst_n);

    // 場景 1：所有櫃檯忙碌 → 不派發
    load_data(4'd10,4'd3,3'b111);

    // 場景 2：櫃檯1 空 → 派到櫃檯1
    load_data(4'd11,4'd2,3'b110);

    // 場景 3：櫃檯2 空 → 派到櫃檯2
    load_data(4'd12,4'd4,3'b101);

    // 場景 4：櫃檯3 空 → 派到櫃檯3
    load_data(4'd13,4'd1,3'b011);

    #100 $finish;
end

// ==== task : 餵一筆資料，並設定 busy 狀態 ====
task load_data(
    input [4:0] num, input [4:0] tim, input [2:0] busy_state
);
begin
    @(negedge clk);
    empty = 0; qn = num; qt = tim; busy = busy_state;
    @(negedge clk);          // 觀察 re / ld?
    @(negedge clk);          // 將 empty 拉高，模擬 FIFO 已被讀走
    empty = 1;
end
endtask

// ==== VCD ====
initial begin
    $dumpfile("dispatcher_tb.vcd");
    $dumpvars(0, dispatcher_tb);
end
endmodule

data/dispatcher_tb.vcd
$date
   Sat May 31 12:09:01 2025
$end
$version
  P.20131013
$end
$timescale
  1ps
$end
$scope module dispatcher_tb $end
$var wire 1 ! re $end
$var wire 1 " ld [2] $end
$var wire 1 # ld [1] $end
$var wire 1 $ ld [0] $end
$var wire 1 % dn [11] $end
$var wire 1 & dn [10] $end
$var wire 1 ' dn [9] $end
$var wire 1 ( dn [8] $end
$var wire 1 ) dn [7] $end
$var wire 1 * dn [6] $end
$var wire 1 + dn [5] $end
$var wire 1 , dn [4] $end
$var wire 1 - dn [3] $end
$var wire 1 . dn [2] $end
$var wire 1 / dn [1] $end
$var wire 1 0 dn [0] $end
$var wire 1 1 dt [11] $end
$var wire 1 2 dt [10] $end
$var wire 1 3 dt [9] $end
$var wire 1 4 dt [8] $end
$var wire 1 5 dt [7] $end
$var wire 1 6 dt [6] $end
$var wire 1 7 dt [5] $end
$var wire 1 8 dt [4] $end
$var wire 1 9 dt [3] $end
$var wire 1 : dt [2] $end
$var wire 1 ; dt [1] $end
$var wire 1 < dt [0] $end
$var reg 1 = clk $end
$var reg 1 > rst_n $end
$var reg 1 ? empty $end
$var reg 4 @ qn [3:0] $end
$var reg 4 A qt [3:0] $end
$var reg 3 B busy [2:0] $end
$scope task load_data $end
$var reg 5 C num [4:0] $end
$var reg 5 D tim [4:0] $end
$var reg 3 E busy_state [2:0] $end
$upscope $end
$scope module dut $end
$var wire 1 F clk $end
$var wire 1 G rst_n $end
$var wire 1 H empty $end
$var wire 1 I qn [3] $end
$var wire 1 J qn [2] $end
$var wire 1 K qn [1] $end
$var wire 1 L qn [0] $end
$var wire 1 M qt [3] $end
$var wire 1 N qt [2] $end
$var wire 1 O qt [1] $end
$var wire 1 P qt [0] $end
$var wire 1 Q busy [2] $end
$var wire 1 R busy [1] $end
$var wire 1 S busy [0] $end
$var reg 1 T re $end
$var reg 3 U ld [2:0] $end
$var reg 12 V dn [11:0] $end
$var reg 12 W dt [11:0] $end
$var integer 32 X i $end
$upscope $end
$upscope $end
$enddefinitions $end
#0
$dumpvars
0)
0(
0'
0:
0&
0;
06
02
0%
08
04
0<
03
09
01
07
05
0T
b0 U
b0 V
b0 W
bx X
0!
0$
0=
0>
1?
b0 @
b0 A
b111 B
bx C
bx D
bx E
0#
0"
00
0/
0.
0-
0,
0+
0*
1S
0M
1R
0I
0J
0O
1Q
0G
0L
0N
0F
1H
0K
0P
$end
#10000
1=
1F
#20000
0=
0F
#30000
1=
1F
#35000
1>
b1010 C
b11 D
b111 E
1G
#40000
0=
0?
b1010 @
b11 A
1I
1O
0F
0H
1K
1P
#50000
1=
1F
#60000
0=
0F
#70000
1=
1F
#80000
0=
1?
b1011 C
b10 D
b110 E
0F
1H
#90000
1=
1F
#100000
0=
0?
b1011 @
b10 A
b110 B
0S
1L
0F
0H
0P
#110000
1=
1F
#112000
1;
1T
b1 U
b1011 V
b10 W
1!
1$
10
1/
1-
#120000
0=
0F
#130000
1=
1F
#132000
1T
b1 U
#140000
0=
1?
b1100 C
b100 D
b101 E
0F
1H
#150000
1=
1F
#152000
0T
b0 U
0!
0$
#160000
0=
0?
b1100 @
b100 A
b101 B
1S
0R
1J
0O
0L
1N
0F
0H
0K
#170000
1=
1F
#172000
1)
16
1T
b10 U
b11001011 V
b1000010 W
1!
1#
1*
#180000
0=
0F
#190000
1=
1F
#192000
1T
b10 U
#200000
0=
1?
b1101 C
b1 D
b11 E
0F
1H
#210000
1=
1F
#212000
0T
b0 U
0!
0#
#220000
0=
0?
b1101 @
b1 A
b11 B
1R
0Q
1L
0N
0F
0H
1P
#230000
1=
1F
#232000
1(
1&
1%
14
1T
b100 U
b110111001011 V
b101000010 W
1!
1"
#240000
0=
0F
#250000
1=
1F
#252000
1T
b100 U
#260000
0=
1?
0F
1H
#270000
1=
1F
#272000
0T
b0 U
0!
0"
