dispatcher.v
//--------------------------------------------------------------
//  dispatcher.v
//  -----------------------------------------------------------
//  1. 功能 : 從佇列 FIFO 取出一筆資料，依序派發給
//            第一個「空閒」的櫃檯 (counter)。
//  2. 規則 : 固定優先權  櫃檯1 → 櫃檯2 → 櫃檯3
//            只要成功派發，就對 FIFO 送出 re=1 讀脈衝。
//  3. 時序 : 以 clk 正緣為基準，所有旗標皆同步重設。
//--------------------------------------------------------------
module dispatcher(clk, rst_n, empty, busy, qn, qt, re, ld, dn, dt);
    parameter DT_SZ = 4;        // 資料大小，預設 4 bits
    parameter CNTER = 3;        // 櫃台數量
	//==================== 時脈 / 重設 =========================
    input  clk;
    input  rst_n;               // 同步低有效

    //==================== 來自 FIFO 的訊號 ====================
    input        empty;         // =1 代表 FIFO 為空
    input  [DT_SZ-1:0] qn;      // 佇列首端客人編號
    input  [DT_SZ-1:0] qt;      // 佇列首端服務時間

    //==================== 各櫃檯忙碌狀態 ======================
    // busy[i] = 1  該櫃檯正在服務，不可派發
    input  [CNTER-1:0] busy;

    //==================== 給 FIFO 的控制 ======================
    output reg   re;            // 讀出脈衝 (HIGH 1 個 clk)

    //==================== 給三個 counter 的載入控制 ===========
    // ld?  : 載入脈衝 (HIGH 1 個 clk)
    // dn?/dt? : 欲載入之 {編號, 時間}
    output reg [CNTER-1:0] ld;
	output reg [DT_SZ-1:0] dn;
	output reg [DT_SZ-1:0] dt;

	// for 迴圈用
	integer i;

	//--------------------------------------------------------------
	//  派發邏輯
	//--------------------------------------------------------------
	always @(posedge clk or negedge rst_n) begin
		if (!rst_n) begin
			// --------- 非同步重設 ---------------------------------
			re  <= 1'b0;
			ld <= {CNTER{1'b0}}; // 脈衝清 0
			dn <= {DT_SZ{1'b0}}; // 暫存清 0
			dt <= {DT_SZ{1'b0}}; // 暫存清 0
		end
		else begin
			#2
			// --------- 預設值：每拍先清脈衝 ----------------------------
			re  <= 1'b0;
			ld <= {CNTER{1'b0}};      // 脈衝清 0
			// --------- 當 FIFO 非空，嘗試派發 ----------------------
			if (!empty) begin:block
				for (i = 0; i < CNTER; i = i + 1) begin
					if (!busy[i]) begin
						re <= 1'b1; 
						ld[i] <= 1'b1;
						dn <= qn;
						dt <= qt;
						disable block; // 找到空位就退出 for 迴圈
					end
				end
				// 若全忙碌：不派發，re=0，資料留在 FIFO
			end
		end
	end
endmodule

dispatcher_tb.v
`timescale 1ns/1ps
module dispatcher_tb;
parameter DT_SZ = 4;        // 資料大小，預設 4 bits
parameter CNTER = 3;        // 櫃台數量
// ==== DUT 連接埠 ====
reg  clk, rst_n;
reg  empty;
reg  [DT_SZ-1:0] qn;
reg  [DT_SZ-1:0] qt;
reg  [CNTER-1:0] busy;

wire re;
wire [CNTER-1:0] ld;
wire [DT_SZ-1:0] dn;
wire [DT_SZ-1:0] dt;

// ==== DUT 例化 ====
dispatcher #(.DT_SZ(DT_SZ), .CNTER(CNTER)) dut (
    .clk(clk), .rst_n(rst_n),
    .empty(empty), .qn(qn), .qt(qt),
    .busy(busy),
    .re(re),
    .ld(ld),
    .dn(dn),
    .dt(dt)
);

// ==== Clock ====
always #10 clk = ~clk;

// ==== Reset ====
initial begin
    clk = 0; rst_n = 0;
    empty = 1; qn = 0; qt = 0; busy = 3'b111;
    #35 rst_n = 1;
end

// ==== Stimulus ====
initial begin
    @(posedge rst_n);

    // 場景 1：所有櫃檯忙碌 → 不派發
    load_data(4'd10,4'd3,3'b111);

    // 場景 2：櫃檯1 空 → 派到櫃檯1
    load_data(4'd11,4'd2,3'b110);

    // 場景 3：櫃檯2 空 → 派到櫃檯2
    load_data(4'd12,4'd4,3'b101);

    // 場景 4：櫃檯3 空 → 派到櫃檯3
    load_data(4'd13,4'd1,3'b011);

    #100 $finish;
end

// ==== task : 餵一筆資料，並設定 busy 狀態 ====
task load_data(
    input [DT_SZ-1:0] num, 
    input [DT_SZ-1:0] tim, 
    input [CNTER-1:0] busy_state
);
begin
    @(negedge clk);
    empty = 0; qn = num; qt = tim; busy = busy_state;
    @(negedge clk);          // 觀察 re / ld?
    @(negedge clk);          // 將 empty 拉高，模擬 FIFO 已被讀走
    empty = 1;
end
endtask

// ==== VCD ====
initial begin
    $dumpfile("dispatcher_tb.vcd");
    $dumpvars(0, dispatcher_tb);
end
endmodule

data/dispatcher_tb.vcd
$date
   Sat May 31 22:51:23 2025
$end
$version
  P.20131013
$end
$timescale
  1ps
$end
$scope module dispatcher_tb $end
$var wire 1 ! re $end
$var wire 1 " ld [2] $end
$var wire 1 # ld [1] $end
$var wire 1 $ ld [0] $end
$var wire 1 % dn [3] $end
$var wire 1 & dn [2] $end
$var wire 1 ' dn [1] $end
$var wire 1 ( dn [0] $end
$var wire 1 ) dt [3] $end
$var wire 1 * dt [2] $end
$var wire 1 + dt [1] $end
$var wire 1 , dt [0] $end
$var reg 1 - clk $end
$var reg 1 . rst_n $end
$var reg 1 / empty $end
$var reg 4 0 qn [3:0] $end
$var reg 4 1 qt [3:0] $end
$var reg 3 2 busy [2:0] $end
$scope task load_data $end
$var reg 4 3 num [3:0] $end
$var reg 4 4 tim [3:0] $end
$var reg 3 5 busy_state [2:0] $end
$upscope $end
$scope module dut $end
$var wire 1 6 clk $end
$var wire 1 7 rst_n $end
$var wire 1 8 empty $end
$var wire 1 9 qn [3] $end
$var wire 1 : qn [2] $end
$var wire 1 ; qn [1] $end
$var wire 1 < qn [0] $end
$var wire 1 = qt [3] $end
$var wire 1 > qt [2] $end
$var wire 1 ? qt [1] $end
$var wire 1 @ qt [0] $end
$var wire 1 A busy [2] $end
$var wire 1 B busy [1] $end
$var wire 1 C busy [0] $end
$var reg 1 D re $end
$var reg 3 E ld [2:0] $end
$var reg 4 F dn [3:0] $end
$var reg 4 G dt [3:0] $end
$var integer 32 H i $end
$upscope $end
$upscope $end
$enddefinitions $end
#0
$dumpvars
0+
0*
0)
0D
b0 E
b0 F
b0 G
bx H
0$
0!
0=
0@
1B
1C
1A
0?
09
0>
0-
0.
1/
b0 0
b0 1
b111 2
bx 3
bx 4
bx 5
0#
0"
0(
0'
0&
0%
0,
07
0<
0;
0:
06
18
$end
#10000
1-
16
#20000
0-
06
#30000
1-
16
#35000
1.
b1010 3
b11 4
b111 5
17
#40000
1@
1?
19
0-
0/
b1010 0
b11 1
1;
06
08
#50000
1-
16
#52000
b11 H
#60000
0-
06
#70000
1-
16
#72000
b11 H
#80000
0-
1/
b1011 3
b10 4
b110 5
06
18
#90000
1-
16
#100000
0@
0C
0-
0/
b1011 0
b10 1
b110 2
1<
06
08
#110000
1-
16
#112000
1+
0D
b1 E
b1011 F
b10 G
b11 H
1$
0!
1(
1'
1%
#120000
0-
06
#130000
1-
16
#132000
0D
b1 E
b11 H
0!
#140000
0-
1/
b1100 3
b100 4
b101 5
06
18
#150000
1-
16
#152000
b0 E
0$
#160000
0B
1C
0?
1>
0-
0/
b1100 0
b100 1
b101 2
0<
0;
1:
06
08
#170000
1-
16
#172000
0+
1*
0D
b10 E
b1100 F
b100 G
b11 H
0!
1#
0(
0'
1&
#180000
0-
06
#190000
1-
16
#192000
0D
b10 E
b11 H
0!
#200000
0-
1/
b1101 3
b1 4
b11 5
06
18
#210000
1-
16
#212000
b0 E
0#
#220000
1@
1B
0A
0>
0-
0/
b1101 0
b1 1
b11 2
1<
06
08
#230000
1-
16
#232000
0*
0D
b100 E
b1101 F
b1 G
b11 H
0!
1"
1(
1,
#240000
0-
06
#250000
1-
16
#252000
0D
b100 E
b11 H
0!
#260000
0-
1/
06
18
#270000
1-
16
#272000
b0 E
0"
