dispatcher.v
//--------------------------------------------------------------
//  dispatcher.v
//  -----------------------------------------------------------
//  1. 功能 : 從佇列 FIFO 取出一筆資料，依序派發給
//            第一個「空閒」的櫃檯 (counter)。
//  2. 規則 : 固定優先權  櫃檯1 → 櫃檯2 → 櫃檯3
//            只要成功派發，就對 FIFO 送出 re=1 讀脈衝。
//  3. 時序 : 以 clk 正緣為基準，所有旗標皆同步重設。
//--------------------------------------------------------------
module dispatcher(clk, rst_n, empty, busy, qn, qt, re, ld1, ld2, ld3, dn1, dt1, dn2, dt2, dn3, dt3);
    //==================== 時脈 / 重設 =========================
    input  clk;
    input  rst_n;              // 同步低有效

    //==================== 來自 FIFO 的訊號 =====================
    input        empty;        // =1 代表 FIFO 為空
    input  [3:0] qn;           // 佇列首端客人編號
    input  [3:0] qt;           // 佇列首端服務時間

    //==================== 各櫃檯忙碌狀態 ======================
    // busy[i] = 1 → 該櫃檯正在服務，不可派發
    input  [2:0] busy;

    //==================== 給 FIFO 的控制 ======================
    output reg   re;           // 讀出脈衝 (HIGH 1 個 clk)

    //==================== 給三個 counter 的載入控制 ===========
    // ld?  : 載入脈衝 (HIGH 1 個 clk)
    // dn?/dt? : 欲載入之 {編號, 時間}
    output reg   ld1, ld2, ld3;
    output reg [3:0] dn1, dn2, dn3;
    output reg [3:0] dt1, dt2, dt3;

	//--------------------------------------------------------------
	//  派發邏輯
	//--------------------------------------------------------------
	always @(posedge clk or negedge rst_n) begin
		if (!rst_n) begin
			// --------- 非同步重設 ---------------------------------
			re  <= 1'b0;
			ld1 <= 1'b0;  dn1 <= 4'd0;  dt1 <= 4'd0;
			ld2 <= 1'b0;  dn2 <= 4'd0;  dt2 <= 4'd0;
			ld3 <= 1'b0;  dn3 <= 4'd0;  dt3 <= 4'd0;
		end
		else begin
			#2
			// --------- 預設值：每拍先清脈衝 ------------------------
			re  <= 1'b0;
			ld1 <= 1'b0;  ld2 <= 1'b0;  ld3 <= 1'b0;

			// --------- 當 FIFO 非空，嘗試派發 ----------------------
			if (!empty) begin
				// --- 優先檢查櫃檯1 ---------------------------------
				if (!busy[0]) begin
					re  <= 1'b1;        // 讀出 FIFO
					ld1 <= 1'b1;        // 觸發櫃檯1 載入
					dn1 <= qn;          // 資料送入櫃檯1
					dt1 <= qt;
				end
				// --- 再檢查櫃檯2 -----------------------------------
				else if (!busy[1]) begin
					re  <= 1'b1;
					ld2 <= 1'b1;
					dn2 <= qn;
					dt2 <= qt;
				end
				// --- 最後檢查櫃檯3 ---------------------------------
				else if (!busy[2]) begin
					re  <= 1'b1;
					ld3 <= 1'b1;
					dn3 <= qn;
					dt3 <= qt;
				end
				// 若全忙碌：不派發，re=0，資料留在 FIFO
			end
		end
	end
endmodule

dispatcher_tb.v
`timescale 1ns/1ps
module dispatcher_tb;
// ==== DUT 連接埠 ====
reg  clk, rst_n;
reg  empty;
reg  [3:0] qn;
reg  [3:0] qt;
reg  [2:0] busy;

wire re, ld1, ld2, ld3;
wire [3:0] dn1, dn2, dn3;
wire [3:0] dt1, dt2, dt3;

// ==== DUT 例化 ====
dispatcher dut (
    .clk(clk), .rst_n(rst_n),
    .empty(empty), .qn(qn), .qt(qt),
    .busy(busy),
    .re(re),
    .ld1(ld1), .ld2(ld2), .ld3(ld3),
    .dn1(dn1), .dt1(dt1),
    .dn2(dn2), .dt2(dt2),
    .dn3(dn3), .dt3(dt3)
);

// ==== Clock ====
always #10 clk = ~clk;

// ==== Reset ====
initial begin
    clk = 0; rst_n = 0;
    empty = 1; qn = 0; qt = 0; busy = 3'b111;
    #35 rst_n = 1;
end

// ==== Stimulus ====
initial begin
    @(posedge rst_n);

    // 場景 1：所有櫃檯忙碌 → 不派發
    load_data(4'd10,4'd3,3'b111);

    // 場景 2：櫃檯1 空 → 派到櫃檯1
    load_data(4'd11,4'd2,3'b110);

    // 場景 3：櫃檯2 空 → 派到櫃檯2
    load_data(4'd12,4'd4,3'b101);

    // 場景 4：櫃檯3 空 → 派到櫃檯3
    load_data(4'd13,4'd1,3'b011);

    #100 $finish;
end

// ==== task : 餵一筆資料，並設定 busy 狀態 ====
task load_data(
    input [4:0] num, input [4:0] tim, input [2:0] busy_state
);
begin
    @(negedge clk);
    empty = 0; qn = num; qt = tim; busy = busy_state;
    @(negedge clk);          // 觀察 re / ld?
    @(negedge clk);          // 將 empty 拉高，模擬 FIFO 已被讀走
    empty = 1;
end
endtask

// ==== VCD ====
initial begin
    $dumpfile("dispatcher_tb.vcd");
    $dumpvars(0, dispatcher_tb);
end
endmodule

data/dispatcher_tb.vcd
$date
   Sat May 31 00:44:03 2025
$end
$version
  P.20131013
$end
$timescale
  1ps
$end
$scope module dispatcher_tb $end
$var wire 1 ! re $end
$var wire 1 " ld1 $end
$var wire 1 # ld2 $end
$var wire 1 $ ld3 $end
$var wire 1 % dn1 [3] $end
$var wire 1 & dn1 [2] $end
$var wire 1 ' dn1 [1] $end
$var wire 1 ( dn1 [0] $end
$var wire 1 ) dn2 [3] $end
$var wire 1 * dn2 [2] $end
$var wire 1 + dn2 [1] $end
$var wire 1 , dn2 [0] $end
$var wire 1 - dn3 [3] $end
$var wire 1 . dn3 [2] $end
$var wire 1 / dn3 [1] $end
$var wire 1 0 dn3 [0] $end
$var wire 1 1 dt1 [3] $end
$var wire 1 2 dt1 [2] $end
$var wire 1 3 dt1 [1] $end
$var wire 1 4 dt1 [0] $end
$var wire 1 5 dt2 [3] $end
$var wire 1 6 dt2 [2] $end
$var wire 1 7 dt2 [1] $end
$var wire 1 8 dt2 [0] $end
$var wire 1 9 dt3 [3] $end
$var wire 1 : dt3 [2] $end
$var wire 1 ; dt3 [1] $end
$var wire 1 < dt3 [0] $end
$var reg 1 = clk $end
$var reg 1 > rst_n $end
$var reg 1 ? empty $end
$var reg 4 @ qn [3:0] $end
$var reg 4 A qt [3:0] $end
$var reg 3 B busy [2:0] $end
$scope task load_data $end
$var reg 5 C num [4:0] $end
$var reg 5 D tim [4:0] $end
$var reg 3 E busy_state [2:0] $end
$upscope $end
$scope module dut $end
$var wire 1 F clk $end
$var wire 1 G rst_n $end
$var wire 1 H empty $end
$var wire 1 I qn [3] $end
$var wire 1 J qn [2] $end
$var wire 1 K qn [1] $end
$var wire 1 L qn [0] $end
$var wire 1 M qt [3] $end
$var wire 1 N qt [2] $end
$var wire 1 O qt [1] $end
$var wire 1 P qt [0] $end
$var wire 1 Q busy [2] $end
$var wire 1 R busy [1] $end
$var wire 1 S busy [0] $end
$var reg 1 T re $end
$var reg 1 U ld1 $end
$var reg 1 V ld2 $end
$var reg 1 W ld3 $end
$var reg 4 X dn1 [3:0] $end
$var reg 4 Y dn2 [3:0] $end
$var reg 4 Z dn3 [3:0] $end
$var reg 4 [ dt1 [3:0] $end
$var reg 4 \ dt2 [3:0] $end
$var reg 4 ] dt3 [3:0] $end
$upscope $end
$upscope $end
$enddefinitions $end
#0
$dumpvars
03
06
0;
0.
0-
07
05
0:
09
08
01
0<
02
04
0!
0=
0>
1?
b0 @
b0 A
b111 B
bx C
bx D
bx E
0"
0#
0$
0(
0'
0&
0%
0,
0+
0*
0)
00
0/
0T
0U
0V
0W
b0 X
b0 Y
b0 Z
b0 [
b0 \
b0 ]
0F
0J
0N
0G
0P
1R
1Q
0L
0I
1H
0K
0O
1S
0M
$end
#10000
1=
1F
#20000
0=
0F
#30000
1=
1F
#35000
1>
b1010 C
b11 D
b111 E
1G
#40000
0=
0?
b1010 @
b11 A
0F
1P
1I
0H
1K
1O
#50000
1=
1F
#60000
0=
0F
#70000
1=
1F
#80000
0=
1?
b1011 C
b10 D
b110 E
0F
1H
#90000
1=
1F
#100000
0=
0?
b1011 @
b10 A
b110 B
0F
0P
1L
0H
0S
#110000
1=
1F
#115000
13
1!
1"
1(
1'
1%
1T
1U
b1011 X
b10 [
#120000
0=
0F
#130000
1=
1F
#135000
1T
1U
#140000
0=
1?
b1100 C
b100 D
b101 E
0F
1H
#150000
1=
1F
#155000
0!
0"
0T
0U
#160000
0=
0?
b1100 @
b100 A
b101 B
0F
1J
1N
0R
0L
0H
0K
0O
1S
#170000
1=
1F
#175000
16
1!
1#
1*
1)
1T
1V
b1100 Y
b100 \
#180000
0=
0F
#190000
1=
1F
#195000
1T
1V
#200000
0=
1?
b1101 C
b1 D
b11 E
0F
1H
#210000
1=
1F
#215000
0!
0#
0T
0V
#220000
0=
0?
b1101 @
b1 A
b11 B
0F
0N
1P
1R
0Q
1L
0H
#230000
1=
1F
#235000
1.
1-
1<
1!
1$
10
1T
1W
b1101 Z
b1 ]
#240000
0=
0F
#250000
1=
1F
#255000
1T
1W
#260000
0=
1?
0F
1H
#270000
1=
1F
#275000
0!
0$
0T
0W
