queue.v
//--------------------------------------------------------------
//  queue.v  -  簡易參數化 FIFO（深度 DEPTH，預設 3）
//  - 用於暫存尚未被派發到櫃檯的客人資料
//  - 每筆資料包含 {客人編號 4-bit, 服務時間 4-bit}
//--------------------------------------------------------------
module queue(clk, rst_n, we, dn, dt, re, qn, qt, full, empty, 
			qdbg); // debug
    parameter DEPTH = 3;					// 佇列深度
    parameter PTR_W = 2;          			// PTR_W = (int)(log2(DEPTH))+1
	// DEPTH = 3 時，PTR_W 固定 2 bit

    input  clk;                          	// 系統時脈
    input  rst_n;                        	// 同步低有效重設

    // 寫入端 (enqueue)
    input         we;                       // we=1 且 ~full 時寫入
    input  [3:0]  dn;                       // data-num  : 客人編號
    input  [3:0]  dt;                       // data-time : 服務時間
    
	// 讀出端 (dequeue)
    input         re;                       // re=1 且 ~empty 時讀出
    output [3:0]  qn;                       // queue-num  : 佇列首端客人編號
    output [3:0]  qt;                       // queue-time : 佇列首端服務時間
    
	// 狀態旗標
    output        full;                     // 佇列已滿
    output        empty;                    // 佇列為空
    
	// 除錯觀察用
    output [23:0] qdbg;

	//--------------------------------------------------------------
	//  內部儲存結構
	//--------------------------------------------------------------
	reg [3:0] nm [0:DEPTH-1];   // 編號暫存
	reg [3:0] tm [0:DEPTH-1];   // 時間暫存

	reg [PTR_W-1:0] hd;   // head 讀指標
	reg [PTR_W-1:0] tl;   // tail 寫指標
	reg [PTR_W-1:0] ct;   // 佇列目前元素數 (0-DEPTH)

	//--------------------------------------------------------------
	//  即時輸出
	//--------------------------------------------------------------
	assign qn    = nm[hd];               // 讀指標指向的資料
	assign qt    = tm[hd];
	assign full  = (ct == DEPTH);        // 已填滿
	assign empty = (ct == 0);            // 沒有資料

	// 串接前三筆資料供波形觀察：{num0,time0,num1,time1,num2,time2}

	assign qdbg = {nm[0],tm[0],nm[1],tm[1],nm[2],tm[2]};
	
	// 給 reset 時的 for 迴圈用
	integer i;

	//--------------------------------------------------------------
	//  寫入 / 讀出 控制邏輯
	//--------------------------------------------------------------
	always @(posedge clk or negedge rst_n) begin
		if (!rst_n) begin
			hd <= 0;
			tl <= 0;
			ct <= 0;
			for (i = 0; i < DEPTH; i = i + 1) begin
				nm[i] <= 4'd0;      // 編號清 0
				tm[i] <= 4'd0;      // 時間清 0
        	end
		end
		else begin
			// 寫入動作 ------------------------------------------------
			if (we && !full) begin
				nm[tl] <= dn;
				tm[tl] <= dt;
				tl <= (tl == DEPTH-1) ? 0 : tl + 1;   // 環形遞增
			end

			// 讀出動作 ------------------------------------------------
			if (re && !empty) begin
				hd <= (hd == DEPTH-1) ? 0 : hd + 1;   // 環形遞增
			end

			// 元素計數器 --------------------------------------------
			case ({we && !full, re && !empty})
				2'b10: ct <= ct + 1;   // 只有寫入
				2'b01: ct <= ct - 1;   // 只有讀出
				default: ;            // 其餘情況 ct 不變
			endcase
		end
	end
endmodule

queue_tb.v
`timescale 1ns/1ps
module queue_tb;
// ==== DUT 連接埠 ====
reg  clk, rst_n;
reg  we,  re;
reg  [3:0] dn;
reg  [3:0] dt;
wire [3:0] qn;
wire [3:0] qt;
wire full, empty;
wire [23:0] qdbg;

// ==== DUT 例化 (DEPTH=3) ====
queue #(.DT_SZ(4), .DEPTH(3), .PTR_W(2)) dut (
    .clk(clk), .rst_n(rst_n),
    .we(we), .dn(dn), .dt(dt),
    .re(re),
    .qn(qn), .qt(qt),
    .full(full), .empty(empty),
	.qdbg(qdbg)
);

// ==== 20 ns Clock ====
always #10 clk = ~clk;

// ==== Reset ====
initial begin
    clk = 0; rst_n = 0;
    we = 0; re = 0; dn = 0; dt = 0;
    #35 rst_n = 1;   // 釋放重設
end

// ==== 寫入 / 讀出 Tasks ====
task write(input [3:0] num, input [3:0] tim);
begin
    @(negedge clk);
    we = 1; dn = num; dt = tim;
    @(negedge clk);
    we = 0; dn = 0;   dt = 0;
end
endtask

task read_one;
begin
    @(negedge clk);
    re = 1;
    @(negedge clk);
    re = 0;
end
endtask

// ==== Stimulus ====
initial begin
    @(posedge rst_n);  // 等待 reset 結束
    // 依序寫入 4 筆 (第 4 筆應因 full 而被忽略)
    write(4'd1,4'd3);
    write(4'd2,4'd2);
    write(4'd3,4'd1);
    write(4'd4,4'd4);  // overflow 測試
    // 依序讀出 3 筆
    #40 read_one;
    #40 read_one;
    #40 read_one;
    // 嘗試對空佇列讀取
    #40 read_one;
    write(4'd5,4'd5);
    #100 $finish;
end

// ==== VCD 波形 ====
initial begin
    $dumpfile("queue_tb.vcd");
    $dumpvars(0, queue_tb);
end
endmodule

data/queue_tb.vcd
$date
   Thu May 29 11:29:36 2025
$end
$version
  P.20131013
$end
$timescale
  1ps
$end
$scope module queue_tb $end
$var wire 1 W qn [3] $end
$var wire 1 X qn [2] $end
$var wire 1 Y qn [1] $end
$var wire 1 Z qn [0] $end
$var wire 1 [ qt [3] $end
$var wire 1 \ qt [2] $end
$var wire 1 ] qt [1] $end
$var wire 1 ^ qt [0] $end
$var wire 1 _ full $end
$var wire 1 ` empty $end
$var wire 1 a qdbg [23] $end
$var wire 1 b qdbg [22] $end
$var wire 1 c qdbg [21] $end
$var wire 1 d qdbg [20] $end
$var wire 1 e qdbg [19] $end
$var wire 1 f qdbg [18] $end
$var wire 1 g qdbg [17] $end
$var wire 1 h qdbg [16] $end
$var wire 1 i qdbg [15] $end
$var wire 1 j qdbg [14] $end
$var wire 1 k qdbg [13] $end
$var wire 1 l qdbg [12] $end
$var wire 1 m qdbg [11] $end
$var wire 1 n qdbg [10] $end
$var wire 1 o qdbg [9] $end
$var wire 1 p qdbg [8] $end
$var wire 1 q qdbg [7] $end
$var wire 1 r qdbg [6] $end
$var wire 1 s qdbg [5] $end
$var wire 1 t qdbg [4] $end
$var wire 1 u qdbg [3] $end
$var wire 1 v qdbg [2] $end
$var wire 1 w qdbg [1] $end
$var wire 1 x qdbg [0] $end
$var reg 1 C clk $end
$var reg 1 D rst_n $end
$var reg 1 E we $end
$var reg 1 F re $end
$var reg 4 G dn [3:0] $end
$var reg 4 H dt [3:0] $end
$scope task write $end
$var reg 4 I num [3:0] $end
$var reg 4 J tim [3:0] $end
$upscope $end
$scope task read_one $end
$upscope $end
$scope module dut $end
$var wire 1 K clk $end
$var wire 1 L rst_n $end
$var wire 1 M we $end
$var wire 1 N dn [3] $end
$var wire 1 O dn [2] $end
$var wire 1 P dn [1] $end
$var wire 1 Q dn [0] $end
$var wire 1 R dt [3] $end
$var wire 1 S dt [2] $end
$var wire 1 T dt [1] $end
$var wire 1 U dt [0] $end
$var wire 1 V re $end
$var wire 1 W qn [3] $end
$var wire 1 X qn [2] $end
$var wire 1 Y qn [1] $end
$var wire 1 Z qn [0] $end
$var wire 1 [ qt [3] $end
$var wire 1 \ qt [2] $end
$var wire 1 ] qt [1] $end
$var wire 1 ^ qt [0] $end
$var wire 1 _ full $end
$var wire 1 ` empty $end
$var wire 1 a qdbg [23] $end
$var wire 1 b qdbg [22] $end
$var wire 1 c qdbg [21] $end
$var wire 1 d qdbg [20] $end
$var wire 1 e qdbg [19] $end
$var wire 1 f qdbg [18] $end
$var wire 1 g qdbg [17] $end
$var wire 1 h qdbg [16] $end
$var wire 1 i qdbg [15] $end
$var wire 1 j qdbg [14] $end
$var wire 1 k qdbg [13] $end
$var wire 1 l qdbg [12] $end
$var wire 1 m qdbg [11] $end
$var wire 1 n qdbg [10] $end
$var wire 1 o qdbg [9] $end
$var wire 1 p qdbg [8] $end
$var wire 1 q qdbg [7] $end
$var wire 1 r qdbg [6] $end
$var wire 1 s qdbg [5] $end
$var wire 1 t qdbg [4] $end
$var wire 1 u qdbg [3] $end
$var wire 1 v qdbg [2] $end
$var wire 1 w qdbg [1] $end
$var wire 1 x qdbg [0] $end
$var reg 12 y nm [3:0] $end
$var reg 12 z tm [3:0] $end
$var reg 2 { hd [1:0] $end
$var reg 2 | tl [1:0] $end
$var reg 2 } ct [1:0] $end
$var integer 32 ~ i $end
$upscope $end
$upscope $end
$enddefinitions $end
#0
$dumpvars
1`
0x
0w
0v
0u
0t
0X
0W
0^
0]
0\
0[
0_
0Y
0C
0D
0E
0F
b0 G
b0 H
bx I
bx J
0m
0n
0g
0e
0d
0j
0c
0o
0r
0h
0f
0l
0k
0s
0q
0p
0i
0Z
0S
0N
0Q
0M
0V
0R
0L
0P
0O
0b
0U
0T
0K
0a
b0 y
b0 z
b0 {
b0 |
b0 }
b11 ~
$end
#10000
1C
1K
b11 ~
#20000
0C
0K
#30000
1C
1K
b11 ~
#35000
1D
b1 I
b11 J
1L
#40000
0C
1E
b1 G
b11 H
1Q
1M
1U
1T
0K
#50000
0`
1^
1]
1C
1g
1d
1h
1Z
1K
b100000000 y
b1100000000 z
b1 |
b1 }
#60000
0C
0E
b0 G
b0 H
b10 I
b10 J
0Q
0M
0U
0T
0K
#70000
1C
1K
#80000
0C
1E
b10 G
b10 H
1M
1P
1T
0K
#90000
1C
1o
1k
1K
b100100000 y
b1100100000 z
b10 |
b10 }
#100000
0C
0E
b0 G
b0 H
b11 I
b1 J
0M
0P
0T
0K
#110000
1C
1K
#120000
0C
1E
b11 G
b1 H
1Q
1M
1P
1U
0K
#130000
1x
1t
1_
1C
1s
1K
b100100011 y
b1100100001 z
b0 |
b11 }
#140000
0C
0E
b0 G
b0 H
b100 I
b100 J
0Q
0M
0P
0U
0K
#150000
1C
1K
#160000
0C
1E
b100 G
b100 H
1S
1M
1O
0K
#170000
1C
1K
#180000
0C
0E
b0 G
b0 H
0S
0M
0O
0K
#190000
1C
1K
#200000
0C
0K
#210000
1C
1K
#220000
0C
1F
1V
0K
#230000
0^
0_
1Y
1C
0Z
1K
b1 {
b10 }
#240000
0C
0F
0V
0K
#250000
1C
1K
#260000
0C
0K
#270000
1C
1K
#280000
0C
1F
1V
0K
#290000
1^
0]
1C
1Z
1K
b10 {
b1 }
#300000
0C
0F
0V
0K
#310000
1C
1K
#320000
0C
0K
#330000
1C
1K
#340000
0C
1F
1V
0K
#350000
1`
1]
0Y
1C
1K
b0 {
b0 }
#360000
0C
0F
0V
0K
#370000
1C
1K
#380000
0C
0K
#390000
1C
1K
#400000
0C
1F
1V
0K
#410000
1C
1K
#420000
0C
0F
b101 I
b101 J
0V
0K
#430000
1C
1K
#440000
0C
1E
b101 G
b101 H
1S
1Q
1M
1O
1U
0K
#450000
0`
1X
0]
1\
1C
0g
1f
1b
1K
b10100100011 y
b10100100001 z
b1 |
b1 }
#460000
0C
0E
b0 G
b0 H
0S
0Q
0M
0O
0U
0K
