counter.v
//--------------------------------------------------------------
//  counter.v
//  -----------------------------------------------------------
//  功能 : 單一櫃台（Counter）之服務狀態機
//         ─ 收到 1-拍脈衝 ld=1 時，載入 {客人編號 dn, 服務時間 dt}
//         ─ busy=1 代表櫃台正在服務；rem 每拍倒數
//         ─ rem 歸零後自動釋放櫃台 (busy<=0) 並將輸出歸 0
//--------------------------------------------------------------
module counter(clk, rst_n, ld, dn, dt, busy, num, rem);
    parameter TIME_W = 4;          // 服務時間位元數，預設 4 bits

    //==================== 時脈 / 重設 =========================
    input  clk;                   // 系統時脈
    input  rst_n;                 // 同步低有效重設

    //==================== 新客人載入介面 ======================
    input         ld;             // 載入脈衝 (HIGH 1 拍)
    input  [3:0]  dn;             // data-num  : 客人編號
    input  [TIME_W-1:0] dt;       // data-time : 服務時間

    //==================== 狀態輸出 ===========================
    output reg        busy;       // =1，櫃台忙碌
    output reg [3:0]  num;        // 現正服務之客人編號	(idle=0)
    output reg [TIME_W-1:0] rem;  // 倒數剩餘時間		(idle=0)

	//--------------------------------------------------------------
	//  主時序區塊
	//  -----------------------------------------------------------
	//  ld=1   : 載入資料並進入忙碌狀態 (busy<=1)
	//  busy=1 : 每拍 rem--；倒數至 0 釋放櫃台 (busy<=0)
	//--------------------------------------------------------------
	always @(posedge clk or negedge rst_n) begin
		if (!rst_n) begin
			// ---------- 非同步重設 --------------------------------
			busy <= 1'b0;
			num  <= 4'd0;
			rem  <= {TIME_W{1'b0}};
		end
		else begin
			if (ld) begin
				// ---------- 進入服務 -------------------------------
				busy <= 1'b1;
				num  <= dn;
				rem  <= dt;
			end
			else if (busy) begin
				// ---------- 服務進行中：倒數 -----------------------
				if (rem > 1)
					rem <= rem - 1'b1;          // 尚未完成
				else begin
					// rem==1 : 下一拍歸 0，釋放櫃台
					busy <= 1'b0;
					num  <= 4'd0;
					rem  <= {TIME_W{1'b0}};
				end
			end
			// idle 狀態 (busy=0 且 ld=0) : 保持輸出為 0
		end
	end
endmodule

dispatcher.v
//--------------------------------------------------------------
//  dispatcher.v
//  -----------------------------------------------------------
//  1. 功能 : 從佇列 FIFO 取出一筆資料，依序派發給
//            第一個「空閒」的櫃檯 (counter)。
//  2. 規則 : 固定優先權  櫃檯1 → 櫃檯2 → 櫃檯3
//            只要成功派發，就對 FIFO 送出 re=1 讀脈衝。
//  3. 時序 : 以 clk 正緣為基準，所有旗標皆同步重設。
//--------------------------------------------------------------
module dispatcher(clk, rst_n, empty, busy, qn, qt, re, ld, dn, dt);
    parameter DT_SZ = 4;        // 資料大小，預設 4 bits
    parameter CNTER = 3;        // 櫃台數量
	//==================== 時脈 / 重設 =========================
    input  clk;
    input  rst_n;               // 同步低有效

    //==================== 來自 FIFO 的訊號 ====================
    input        empty;         // =1 代表 FIFO 為空
    input  [DT_SZ-1:0] qn;      // 佇列首端客人編號
    input  [DT_SZ-1:0] qt;      // 佇列首端服務時間

    //==================== 各櫃檯忙碌狀態 ======================
    // busy[i] = 1  該櫃檯正在服務，不可派發
    input  [CNTER-1:0] busy;

    //==================== 給 FIFO 的控制 ======================
    output reg   re;            // 讀出脈衝 (HIGH 1 個 clk)

    //==================== 給三個 counter 的載入控制 ===========
    // ld?  : 載入脈衝 (HIGH 1 個 clk)
    // dn?/dt? : 欲載入之 {編號, 時間}
    output reg [CNTER-1:0] ld;
	output reg [DT_SZ-1:0] dn;
	output reg [DT_SZ-1:0] dt;

	// for 迴圈用
	integer i;

	//--------------------------------------------------------------
	//  派發邏輯
	//--------------------------------------------------------------
	always @(posedge clk or negedge rst_n) begin
		if (!rst_n) begin
			// --------- 非同步重設 ---------------------------------
			re  <= 1'b0;
			ld <= {CNTER{1'b0}}; // 脈衝清 0
			dn <= {DT_SZ{1'b0}}; // 暫存清 0
			dt <= {DT_SZ{1'b0}}; // 暫存清 0
		end
		else begin
			#2
			// --------- 預設值：每拍先清脈衝 ----------------------------
			re  <= 1'b0;
			ld <= {CNTER{1'b0}};      // 脈衝清 0
			// --------- 當 FIFO 非空，嘗試派發 ----------------------
			if (!empty) begin:block
				for (i = 0; i < CNTER; i = i + 1) begin
					if (!busy[i]) begin
						re <= 1'b1; 
						ld[i] <= 1'b1;
						dn <= qn;
						dt <= qt;
						disable block; // 找到空位就退出 for 迴圈
					end
				end
				// 若全忙碌：不派發，re=0，資料留在 FIFO
			end
		end
	end
endmodule

queue.v
//--------------------------------------------------------------
//  queue.v  -  簡易參數化 FIFO（深度 DEPTH，預設 3）
//  - 用於暫存尚未被派發到櫃檯的客人資料
//  - 每筆資料包含 {客人編號 4-bit, 服務時間 4-bit}
//--------------------------------------------------------------
module queue(clk, rst_n, we, dn, dt, re, qn, qt, full, empty, qdbg);
    parameter DT_SZ = 4;					// 資料大小，預設 4 bits
    parameter DEPTH = 3;					// 佇列深度
    parameter PTR_W = 2;          			// PTR_W = (int)(log2(DEPTH))+1
	// DEPTH = 3 時，PTR_W 固定 2 bit

    input  clk;                          	// 系統時脈
    input  rst_n;                        	// 同步低有效重設

    // 寫入端 (enqueue)
    input         		we;                 // we=1 且 ~full 時寫入
    input  [DT_SZ-1:0]  dn;                 // data-num  : 客人編號
    input  [DT_SZ-1:0]  dt;                 // data-time : 服務時間
    
	// 讀出端 (dequeue)
    input         		re;                 // re=1 且 ~empty 時讀出
    output [DT_SZ-1:0]  qn;                 // queue-num  : 佇列首端客人編號
    output [DT_SZ-1:0]  qt;                 // queue-time : 佇列首端服務時間
    
	// 狀態旗標
    output full;                            // 佇列已滿
    output empty;                           // 佇列為空
    
	//--------------------------------------------------------------
	//  內部儲存結構
	//--------------------------------------------------------------
	reg [DT_SZ-1:0] nm [0:DEPTH-1];   // 編號暫存
	reg [DT_SZ-1:0] tm [0:DEPTH-1];   // 時間暫存

	reg [PTR_W-1:0] hd;   // head 讀指標
	reg [PTR_W-1:0] tl;   // tail 寫指標
	reg [PTR_W-1:0] ct;   // 佇列目前元素數 (0-DEPTH)

	//--------------------------------------------------------------
	//  即時輸出
	//--------------------------------------------------------------
	assign qn    = nm[hd];               // 讀指標指向的資料
	assign qt    = tm[hd];
	assign full  = (ct == DEPTH);        // 已填滿
	assign empty = (ct == 0);            // 沒有資料
	
	// for 迴圈用
	integer i;

	// 串接資料供波形觀察
    output reg [DEPTH*2*DT_SZ-1:0] qdbg;
    always @(hd or tl) begin
		qdbg = {DEPTH*2*DT_SZ{1'b0}};
        for(i = 0; i < ct; i = i + 1) begin
            qdbg = {qdbg, nm[(hd+i)%DEPTH], tm[(hd+i)%DEPTH]};
        end
		for(     ; i < DEPTH; i = i + 1) begin
            qdbg = {qdbg, 8'd0};
		end
    end

	//--------------------------------------------------------------
	//  寫入 / 讀出 控制邏輯
	//--------------------------------------------------------------
	always @(posedge clk or negedge rst_n) begin
		if (!rst_n) begin
			hd <= 0;
			tl <= 0;
			ct <= 0;
			for (i = 0; i < DEPTH; i = i + 1) begin
				nm[i] <= {DT_SZ{1'b0}};      // 編號清 0
				tm[i] <= {DT_SZ{1'b0}};      // 時間清 0
        	end
		end
		else begin
			// 寫入動作 ------------------------------------------------
			if (we && !full) begin
				nm[tl] <= dn;
				tm[tl] <= dt;
				tl <= (tl == DEPTH-1) ? 0 : tl + 1;   // 環形遞增
			end

			// 讀出動作 ------------------------------------------------
			if (re && !empty) begin
				hd <= (hd == DEPTH-1) ? 0 : hd + 1;   // 環形遞增
			end

			// 元素計數器 --------------------------------------------
			case ({we && !full, re && !empty})
				2'b10: ct <= ct + 1;   // 只有寫入
				2'b01: ct <= ct - 1;   // 只有讀出
				default: ;             // 其餘情況 ct 不變
			endcase
		end
	end
endmodule

top.v
//--------------------------------------------------------------
//  top.v  -  Queue / Dispatcher / Counter 整合測試平台
//           (針對 ISE Design Suite 14.7 產生)
//--------------------------------------------------------------
//  系統概要：
//  -----------------------------------------------------------
//  1. 來源：外部會以 in_valid=1 送入 {客人編號 in_num[3:0], 服務時間 in_time[3:0]}
//  2. 流程：
//      2-1. queue   : 尚無櫃檯可用時，資料先進 FIFO (深度=3)
//      2-2. dispatcher : 偵測空櫃檯，從 queue 取值派發 (固定優先權 櫃檯1->2->3)
//      2-3. counter : 櫃檯內部倒數；完成後自動 idle
//  3. 輸出：
//      num1/clk1 ... num3/clk3   : 各櫃檯現正服務客人編號 / 剩餘倒數
//      queue                     : FIFO 內容除錯觀察 (24-bit)
//--------------------------------------------------------------
module top(clk, rst_n, in_valid, in_num, in_time, num1, clk1, num2, clk2, num3, clk3, qdbg
			// , fifo_re, ld, busy, fifo_full, fifo_emp, fifo_num, fifo_tim, dn, dt // debug
			);
    parameter DT_SZ = 4;		  // 資料大小，預設 4 bits
    parameter DEPTH = 3;		  // queue 佇列深度，預設 3 個客人 (24 bits)
    parameter PTR_W = 2;          // PTR_W = (int)(log2(DEPTH))+1
    parameter CNTER = 3;          // 櫃台數量

    //==================== 時脈 / 重設 =========================
    input  clk;                   // 20 ns 週期 (50 MHz)
    input  rst_n;                 // 同步低有效

    //==================== 來源輸入 ============================
    input               in_valid; // =1 時 in_num / in_time 有效
    input  [DT_SZ-1:0]  in_num;   // 客人編號 (0 為空)
    input  [DT_SZ-1:0]  in_time;  // 服務時間 (1~15)

    //==================== 櫃檯狀態輸出 ========================
    output [DT_SZ-1:0]  num1;     // 櫃檯1 現正服務客人
    output [DT_SZ-1:0]  clk1;     // 櫃檯1 剩餘時間
    output [DT_SZ-1:0]  num2;
    output [DT_SZ-1:0]  clk2;
    output [DT_SZ-1:0]  num3;
    output [DT_SZ-1:0]  clk3;

    //==================== FIFO 佇列除錯用 ====================
	// 觀察用
    output [DEPTH*2*DT_SZ-1:0] qdbg;

	//--------------------------------------------------------------
	//  內部線路宣告
	//--------------------------------------------------------------
	wire              fifo_re;              // dispatcher 對 FIFO 的讀脈衝
	wire [CNTER-1:0]  ld;                   // dispatcher -> counter 的載入
	wire [CNTER-1:0]  busy;                 // counters 忙碌旗標
	wire        	  fifo_full, fifo_emp;  // FIFO 滿 / 空
	wire [DT_SZ-1:0]  fifo_num;             // queue 輸出編號
	wire [DT_SZ-1:0]  fifo_tim;             // queue 輸出時間
	wire [DT_SZ-1:0]  dn;        	        // 發送至 counter 的編號
	wire [DT_SZ-1:0]  dt;        	        // 發送至 counter 的時間

	//--------------------------------------------------------------
	//  模組例化
	//--------------------------------------------------------------
	//  1. 佇列 FIFO ---------------------------------------------
	// in_valid = 1，上層總是嘗試寫入，queue 內部會判斷 full
	// 深度固定為 3 (可參數化)
	queue #(DT_SZ, DEPTH, PTR_W) u_queue (
		clk, rst_n, in_valid, in_num, in_time, 
		fifo_re, fifo_num, fifo_tim, fifo_full, fifo_emp, qdbg);

	//  2. 調度器 Dispatcher -------------------------------------
	// busy = {b3,b2,b1}
	dispatcher #(DT_SZ, CNTER) u_disp (
		clk, rst_n, fifo_emp, busy, fifo_num, fifo_tim, fifo_re, ld, dn, dt);

	//  3. 三個櫃檯 Counter --------------------------------------
	//      counter#1
	counter u_c1 (clk, rst_n, ld[0], dn, dt, busy[0], num1, clk1);
	//      counter#2
	counter u_c2 (clk, rst_n, ld[1], dn, dt, busy[1], num2, clk2);
	//      counter#3
	counter u_c3 (clk, rst_n, ld[2], dn, dt, busy[2], num3, clk3);
endmodule

top_tb.v
`timescale 1ns / 1ps
module top_tb;
    parameter DT_SZ = 4;		  // 資料大小，預設 4 bits
    parameter DEPTH = 3;		  // queue 佇列深度，預設 3 個客人 (24 bits)
    parameter PTR_W = 2;          // PTR_W = (int)(log2(DEPTH))+1
    parameter CNTER = 3;          // 櫃台數量

	// Inputs
	reg clk;
	reg rst_n;
	reg in_valid;
	reg [DT_SZ-1:0] in_num;
	reg [DT_SZ-1:0] in_time;

	// Outputs
	wire [DT_SZ-1:0] num1;
	wire [DT_SZ-1:0] clk1;
	wire [DT_SZ-1:0] num2;
	wire [DT_SZ-1:0] clk2;
	wire [DT_SZ-1:0] num3;
	wire [DT_SZ-1:0] clk3;
	wire [DEPTH*2*DT_SZ-1:0] qdbg;
	// wire fifo_re;
	// wire [CNTER-1:0] ld;
	// wire [CNTER-1:0] busy;
	// wire fifo_full;
	// wire fifo_emp;
	// wire [DT_SZ-1:0] fifo_num;
	// wire [DT_SZ-1:0] fifo_tim;
	// wire [DT_SZ-1:0] dn;
	// wire [DT_SZ-1:0] dt;

	// Instantiate the Unit Under Test (UUT)
	top #(.DT_SZ(DT_SZ), .DEPTH(DEPTH), .PTR_W(PTR_W), .CNTER(CNTER)) uut (
		.clk(clk), 
		.rst_n(rst_n), 
		.in_valid(in_valid), 
		.in_num(in_num), 
		.in_time(in_time), 
		.num1(num1), 
		.clk1(clk1), 
		.num2(num2), 
		.clk2(clk2), 
		.num3(num3), 
		.clk3(clk3), 
		.qdbg(qdbg)
		// ,.fifo_re(fifo_re), 
		// .ld(ld), 
		// .busy(busy), 
		// .fifo_full(fifo_full), 
		// .fifo_emp(fifo_emp), 
		// .fifo_num(fifo_num), 
		// .fifo_tim(fifo_tim), 
		// .dn(dn), 
		// .dt(dt)
	);

//==== Clock : 20 ns 週期 ======================================
always #10 clk = ~clk;

//==== Reset ===================================================
initial begin
    clk = 0;
    rst_n = 0;
    in_valid = 0;
    in_num = 0;
    in_time = 0;
    #35 rst_n = 1;           // 釋放重設
end

//==== 送客人 Task =============================================
task send_cust;
    input [DT_SZ-1:0] num;
    input [DT_SZ-1:0] tim;
begin
    @(negedge clk);
    in_valid = 1;
    in_num   = num;
    in_time  = tim;
    @(negedge clk);
    in_valid = 0;
    in_num   = 0;
    in_time  = 0;
end
endtask

//==== Stimulus ================================================
initial begin
    @(posedge rst_n);        // 等待重設結束
    #20;

    // ── 先填滿三個櫃台 ───────────────────────────────
    send_cust(4'd1, 4'd8);
    send_cust(4'd2, 4'd8);
    send_cust(4'd3, 4'd8);

    // ── 再塞進 FIFO（深度 3）────────────────────────
    send_cust(4'd4, 4'd1);
    send_cust(4'd5, 4'd5);
    send_cust(4'd6, 4'd2);

    // ── 佇列已滿，以下客人應被丟棄 ──────────────────
    send_cust(4'd7, 4'd3);

    // ── 等待部分櫃台釋放，再送新客人 ────────────────
    #500;
    send_cust(4'd8, 4'd2);
    send_cust(4'd9, 4'd6);

    // ── 結束模擬 ───────────────────────────────────
    #1000 $finish;
end

//==== 波形輸出 (VCD) ==========================================
initial begin
    $dumpfile("top_tb.vcd");
    $dumpvars(0, top_tb);
end

endmodule

data/top_tb.vcd
$date
   Sat May 31 23:32:42 2025
$end
$version
  P.20131013
$end
$timescale
  1ps
$end
$scope module top_tb $end
$var wire 1 c num1 [3] $end
$var wire 1 d num1 [2] $end
$var wire 1 e num1 [1] $end
$var wire 1 f num1 [0] $end
$var wire 1 g clk1 [3] $end
$var wire 1 h clk1 [2] $end
$var wire 1 i clk1 [1] $end
$var wire 1 j clk1 [0] $end
$var wire 1 k num2 [3] $end
$var wire 1 l num2 [2] $end
$var wire 1 m num2 [1] $end
$var wire 1 n num2 [0] $end
$var wire 1 o clk2 [3] $end
$var wire 1 p clk2 [2] $end
$var wire 1 q clk2 [1] $end
$var wire 1 r clk2 [0] $end
$var wire 1 s num3 [3] $end
$var wire 1 t num3 [2] $end
$var wire 1 u num3 [1] $end
$var wire 1 v num3 [0] $end
$var wire 1 w clk3 [3] $end
$var wire 1 x clk3 [2] $end
$var wire 1 y clk3 [1] $end
$var wire 1 z clk3 [0] $end
$var wire 1 { qdbg [23] $end
$var wire 1 | qdbg [22] $end
$var wire 1 } qdbg [21] $end
$var wire 1 ~ qdbg [20] $end
$var wire 1 !! qdbg [19] $end
$var wire 1 "! qdbg [18] $end
$var wire 1 #! qdbg [17] $end
$var wire 1 $! qdbg [16] $end
$var wire 1 %! qdbg [15] $end
$var wire 1 &! qdbg [14] $end
$var wire 1 '! qdbg [13] $end
$var wire 1 (! qdbg [12] $end
$var wire 1 )! qdbg [11] $end
$var wire 1 *! qdbg [10] $end
$var wire 1 +! qdbg [9] $end
$var wire 1 ,! qdbg [8] $end
$var wire 1 -! qdbg [7] $end
$var wire 1 .! qdbg [6] $end
$var wire 1 /! qdbg [5] $end
$var wire 1 0! qdbg [4] $end
$var wire 1 1! qdbg [3] $end
$var wire 1 2! qdbg [2] $end
$var wire 1 3! qdbg [1] $end
$var wire 1 4! qdbg [0] $end
$var reg 1 Q clk $end
$var reg 1 R rst_n $end
$var reg 1 S in_valid $end
$var reg 4 T in_num [3:0] $end
$var reg 4 U in_time [3:0] $end
$scope task send_cust $end
$var reg 4 V num [3:0] $end
$var reg 4 W tim [3:0] $end
$upscope $end
$scope module uut $end
$var wire 1 <" clk $end
$var wire 1 =" rst_n $end
$var wire 1 P! in_valid $end
$var wire 1 Q! in_num [3] $end
$var wire 1 R! in_num [2] $end
$var wire 1 S! in_num [1] $end
$var wire 1 T! in_num [0] $end
$var wire 1 U! in_time [3] $end
$var wire 1 V! in_time [2] $end
$var wire 1 W! in_time [1] $end
$var wire 1 X! in_time [0] $end
$var wire 1 c num1 [3] $end
$var wire 1 d num1 [2] $end
$var wire 1 e num1 [1] $end
$var wire 1 f num1 [0] $end
$var wire 1 g clk1 [3] $end
$var wire 1 h clk1 [2] $end
$var wire 1 i clk1 [1] $end
$var wire 1 j clk1 [0] $end
$var wire 1 k num2 [3] $end
$var wire 1 l num2 [2] $end
$var wire 1 m num2 [1] $end
$var wire 1 n num2 [0] $end
$var wire 1 o clk2 [3] $end
$var wire 1 p clk2 [2] $end
$var wire 1 q clk2 [1] $end
$var wire 1 r clk2 [0] $end
$var wire 1 s num3 [3] $end
$var wire 1 t num3 [2] $end
$var wire 1 u num3 [1] $end
$var wire 1 v num3 [0] $end
$var wire 1 w clk3 [3] $end
$var wire 1 x clk3 [2] $end
$var wire 1 y clk3 [1] $end
$var wire 1 z clk3 [0] $end
$var wire 1 { qdbg [23] $end
$var wire 1 | qdbg [22] $end
$var wire 1 } qdbg [21] $end
$var wire 1 ~ qdbg [20] $end
$var wire 1 !! qdbg [19] $end
$var wire 1 "! qdbg [18] $end
$var wire 1 #! qdbg [17] $end
$var wire 1 $! qdbg [16] $end
$var wire 1 %! qdbg [15] $end
$var wire 1 &! qdbg [14] $end
$var wire 1 '! qdbg [13] $end
$var wire 1 (! qdbg [12] $end
$var wire 1 )! qdbg [11] $end
$var wire 1 *! qdbg [10] $end
$var wire 1 +! qdbg [9] $end
$var wire 1 ,! qdbg [8] $end
$var wire 1 -! qdbg [7] $end
$var wire 1 .! qdbg [6] $end
$var wire 1 /! qdbg [5] $end
$var wire 1 0! qdbg [4] $end
$var wire 1 1! qdbg [3] $end
$var wire 1 2! qdbg [2] $end
$var wire 1 3! qdbg [1] $end
$var wire 1 4! qdbg [0] $end
$var wire 1 Y! fifo_re $end
$var wire 1 >" ld [2] $end
$var wire 1 0" ld [1] $end
$var wire 1 "" ld [0] $end
$var wire 1 v! busy [2] $end
$var wire 1 w! busy [1] $end
$var wire 1 x! busy [0] $end
$var wire 1 b! fifo_full $end
$var wire 1 m! fifo_emp $end
$var wire 1 n! fifo_num [3] $end
$var wire 1 o! fifo_num [2] $end
$var wire 1 p! fifo_num [1] $end
$var wire 1 q! fifo_num [0] $end
$var wire 1 r! fifo_tim [3] $end
$var wire 1 s! fifo_tim [2] $end
$var wire 1 t! fifo_tim [1] $end
$var wire 1 u! fifo_tim [0] $end
$var wire 1 ?" dn [3] $end
$var wire 1 @" dn [2] $end
$var wire 1 A" dn [1] $end
$var wire 1 B" dn [0] $end
$var wire 1 C" dt [3] $end
$var wire 1 D" dt [2] $end
$var wire 1 E" dt [1] $end
$var wire 1 F" dt [0] $end
$scope module u_queue $end
$var wire 1 <" clk $end
$var wire 1 =" rst_n $end
$var wire 1 P! we $end
$var wire 1 Q! dn [3] $end
$var wire 1 R! dn [2] $end
$var wire 1 S! dn [1] $end
$var wire 1 T! dn [0] $end
$var wire 1 U! dt [3] $end
$var wire 1 V! dt [2] $end
$var wire 1 W! dt [1] $end
$var wire 1 X! dt [0] $end
$var wire 1 Y! re $end
$var wire 1 n! qn [3] $end
$var wire 1 o! qn [2] $end
$var wire 1 p! qn [1] $end
$var wire 1 q! qn [0] $end
$var wire 1 r! qt [3] $end
$var wire 1 s! qt [2] $end
$var wire 1 t! qt [1] $end
$var wire 1 u! qt [0] $end
$var wire 1 b! full $end
$var wire 1 m! empty $end
$var reg 12 d! nm [3:0] $end
$var reg 12 e! tm [3:0] $end
$var reg 2 f! hd [1:0] $end
$var reg 2 g! tl [1:0] $end
$var reg 2 h! ct [1:0] $end
$var integer 32 i! i $end
$var reg 24 j! qdbg [23:0] $end
$upscope $end
$scope module u_disp $end
$var wire 1 <" clk $end
$var wire 1 =" rst_n $end
$var wire 1 m! empty $end
$var wire 1 n! qn [3] $end
$var wire 1 o! qn [2] $end
$var wire 1 p! qn [1] $end
$var wire 1 q! qn [0] $end
$var wire 1 r! qt [3] $end
$var wire 1 s! qt [2] $end
$var wire 1 t! qt [1] $end
$var wire 1 u! qt [0] $end
$var wire 1 v! busy [2] $end
$var wire 1 w! busy [1] $end
$var wire 1 x! busy [0] $end
$var reg 1 y! re $end
$var reg 3 z! ld [2:0] $end
$var reg 4 {! dn [3:0] $end
$var reg 4 |! dt [3:0] $end
$var integer 32 }! i $end
$scope begin block $end
$upscope $end
$upscope $end
$scope module u_c1 $end
$var wire 1 <" clk $end
$var wire 1 =" rst_n $end
$var wire 1 "" ld $end
$var wire 1 ?" dn [3] $end
$var wire 1 @" dn [2] $end
$var wire 1 A" dn [1] $end
$var wire 1 B" dn [0] $end
$var wire 1 C" dt [3] $end
$var wire 1 D" dt [2] $end
$var wire 1 E" dt [1] $end
$var wire 1 F" dt [0] $end
$var reg 1 +" busy $end
$var reg 4 ," num [3:0] $end
$var reg 4 -" rem [3:0] $end
$upscope $end
$scope module u_c2 $end
$var wire 1 <" clk $end
$var wire 1 =" rst_n $end
$var wire 1 0" ld $end
$var wire 1 ?" dn [3] $end
$var wire 1 @" dn [2] $end
$var wire 1 A" dn [1] $end
$var wire 1 B" dn [0] $end
$var wire 1 C" dt [3] $end
$var wire 1 D" dt [2] $end
$var wire 1 E" dt [1] $end
$var wire 1 F" dt [0] $end
$var reg 1 9" busy $end
$var reg 4 :" num [3:0] $end
$var reg 4 ;" rem [3:0] $end
$upscope $end
$scope module u_c3 $end
$var wire 1 <" clk $end
$var wire 1 =" rst_n $end
$var wire 1 >" ld $end
$var wire 1 ?" dn [3] $end
$var wire 1 @" dn [2] $end
$var wire 1 A" dn [1] $end
$var wire 1 B" dn [0] $end
$var wire 1 C" dt [3] $end
$var wire 1 D" dt [2] $end
$var wire 1 E" dt [1] $end
$var wire 1 F" dt [0] $end
$var reg 1 G" busy $end
$var reg 4 H" num [3:0] $end
$var reg 4 I" rem [3:0] $end
$upscope $end
$upscope $end
$upscope $end
$enddefinitions $end
#0
$dumpvars
0d
0c
0j
0i
0h
0g
0n
0f
0e
0Q
0R
0S
b0 T
b0 U
bx V
bx W
0w
0z
0-!
0u
0t
0s
0y
0/!
0x
04!
02!
03!
00!
0v
0.!
01!
0o
0m
0l
0k
0r
0q
0p
0'!
0{
0~
0Y!
0>"
0x!
0o!
0s!
0(!
0r!
0*!
0B"
0A"
0@"
0b!
0&!
0"!
0v!
0!!
0+!
1m!
0n!
0p!
0#!
0|
0""
0)!
0}
0w!
0%!
0u!
0t!
0,!
0$!
00"
0q!
0T!
0W!
0P!
0?"
0Q!
0V!
0S!
0U!
0E"
0D"
0F"
0C"
0<"
0="
0X!
0R!
b0 d!
b0 e!
b0 f!
b0 g!
b0 h!
b11 i!
b0 j!
0y!
b0 z!
b0 {!
b0 |!
bx }!
0+"
b0 ,"
b0 -"
09"
b0 :"
b0 ;"
0G"
b0 H"
b0 I"
$end
#10000
1Q
1<"
b11 i!
#20000
0Q
0<"
#30000
1Q
1<"
b11 i!
#35000
1R
1="
#40000
0Q
0<"
#50000
1Q
1<"
#55000
b1 V
b1000 W
#60000
0Q
1S
b1 T
b1000 U
1T!
1P!
1U!
0<"
#70000
1Q
1~
1r!
1!!
0m!
1q!
1<"
b100000000 d!
b100000000000 e!
b1 g!
b1 h!
b11 i!
b110000000000000000000 j!
#72000
1Y!
1B"
1""
1C"
1y!
b1 z!
b1 {!
b1000 |!
b0 }!
#80000
0Q
0S
b0 T
b0 U
b10 V
0T!
0P!
0U!
0<"
#90000
1g
1f
1Q
0~
1x!
0r!
0!!
1m!
0q!
1<"
b1 f!
b0 h!
b11 i!
b0 j!
1+"
b1 ,"
b1000 -"
#92000
0Y!
0""
0y!
b0 z!
#100000
0Q
1S
b10 T
b1000 U
1P!
1S!
1U!
0<"
#110000
1j
1i
1h
0g
1Q
1r!
1!!
0m!
1p!
1}
1<"
b100100000 d!
b100010000000 e!
b10 g!
b1 h!
b11 i!
b1010000000000000000000 j!
b111 -"
#112000
1Y!
0B"
1A"
10"
1y!
b10 z!
b10 {!
b1 }!
#120000
0Q
0S
b0 T
b0 U
b11 V
0P!
0S!
0U!
0<"
#130000
0j
1Q
1o
1m
0r!
0!!
1m!
0p!
0}
1w!
1<"
b10 f!
b0 h!
b11 i!
b0 j!
b110 -"
19"
b10 :"
b1000 ;"
#132000
0Y!
00"
0y!
b0 z!
#140000
0Q
1S
b11 T
b1000 U
1T!
1P!
1S!
1U!
0<"
#150000
1j
0i
1Q
0o
1r
1q
1p
1~
1r!
1!!
0m!
1p!
1}
1q!
1<"
b100100011 d!
b100010001000 e!
b0 g!
b1 h!
b11 i!
b1110000000000000000000 j!
b101 -"
b111 ;"
#152000
1Y!
1>"
1B"
1y!
b100 z!
b11 {!
b10 }!
#160000
0Q
0S
b0 T
b0 U
b100 V
b1 W
0T!
0P!
0S!
0U!
0<"
#170000
0j
1Q
1w
1u
1v
0r
0~
1v!
0!!
1m!
0p!
0}
1<"
b0 f!
b0 h!
b11 i!
b0 j!
b100 -"
b110 ;"
1G"
b11 H"
b1000 I"
#172000
0Y!
0>"
0y!
b0 z!
#180000
0Q
1S
b100 T
b1 U
1P!
0<"
1X!
1R!
#190000
1j
1i
0h
1Q
0w
1z
1y
1x
1r
0q
1o!
0r!
0m!
1|
1u!
1$!
0q!
1<"
b10000100011 d!
b110001000 e!
b1 g!
b1 h!
b11 i!
b10000010000000000000000 j!
b11 -"
b101 ;"
b111 I"
#192000
b11 }!
#200000
0Q
0S
b0 T
b0 U
b101 V
b101 W
0P!
0<"
0X!
0R!
#210000
0j
1Q
0z
0r
1<"
b10 -"
b100 ;"
b110 I"
#212000
b11 }!
#220000
0Q
1S
b101 T
b101 U
1T!
1P!
1V!
0<"
1X!
1R!
#230000
1j
0i
1Q
1z
0y
1r
1q
0p
1(!
1*!
1&!
1,!
1<"
b10001010011 d!
b101011000 e!
b10 g!
b10 h!
b11 i!
b10000010101010100000000 j!
b1 -"
b11 ;"
b101 I"
#232000
b11 }!
#240000
0Q
0S
b0 T
b0 U
b110 V
b10 W
0T!
0P!
0V!
0<"
0X!
0R!
#250000
0j
0f
1Q
0z
0r
0x!
1<"
0+"
b0 ,"
b0 -"
b10 ;"
b100 I"
#252000
1Y!
0B"
0A"
1@"
1""
1F"
0C"
1y!
b1 z!
b100 {!
b1 |!
b0 }!
#260000
0Q
1S
b110 T
b10 U
1W!
1P!
1S!
0<"
1R!
#270000
1d
1j
1Q
1z
1y
0x
1r
0q
1'!
1~
1x!
1s!
0(!
0*!
1"!
1+!
0,!
1q!
1<"
b10001010110 d!
b101010010 e!
b1 f!
b0 g!
b11 i!
b10101010110001000000000 j!
1+"
b100 ,"
b1 -"
b1 ;"
b11 I"
#272000
0Y!
0""
0y!
b0 z!
b11 }!
#280000
0Q
0S
b0 T
b0 U
b111 V
b11 W
0W!
0P!
0S!
0<"
0R!
#290000
0d
0j
1Q
0z
0m
0r
0x!
0w!
1<"
0+"
b0 ,"
b0 -"
09"
b0 :"
b0 ;"
b10 I"
#292000
1Y!
1B"
1""
1D"
1y!
b1 z!
b101 {!
b101 |!
b0 }!
#300000
0Q
1S
b111 T
b11 U
1T!
1W!
1P!
1S!
0<"
1X!
1R!
#310000
1d
1j
1h
1f
1Q
1z
0y
0~
1x!
0s!
1(!
0"!
1p!
1#!
1}
0u!
1t!
1,!
0$!
0q!
1<"
b11101010110 d!
b1101010010 e!
b10 f!
b1 g!
b11 i!
b11000100111001100000000 j!
1+"
b101 ,"
b101 -"
b1 I"
#312000
0B"
1A"
0""
10"
1E"
0D"
0F"
1y!
b10 z!
b110 {!
b10 |!
b1 }!
#320000
0Q
0S
b0 T
b0 U
0T!
0W!
0P!
0S!
0<"
0X!
0R!
#330000
0j
1Q
0z
0u
0v
1m
1l
1q
0'!
1~
0(!
0&!
0v!
0+!
1w!
1u!
0,!
1$!
1q!
1<"
b0 f!
b1 h!
b11 i!
b11100110000000000000000 j!
b100 -"
19"
b110 :"
b10 ;"
0G"
b0 H"
b0 I"
#332000
1>"
1B"
00"
1F"
1y!
b100 z!
b111 {!
b11 |!
b10 }!
#340000
0Q
0<"
#350000
1j
1i
0h
1Q
1z
1u
1t
1y
1v
1r
0q
0~
1s!
1v!
1m!
0p!
0#!
0|
0}
0t!
0$!
1<"
b1 f!
b0 h!
b11 i!
b0 j!
b11 -"
b1 ;"
1G"
b111 H"
b11 I"
#352000
0Y!
0>"
0y!
b0 z!
#360000
0Q
0<"
#370000
0j
1Q
0z
0m
0l
0r
0w!
1<"
b10 -"
09"
b0 :"
b0 ;"
b10 I"
#380000
0Q
0<"
#390000
1j
0i
1Q
1z
0y
1<"
b1 -"
b1 I"
#400000
0Q
0<"
#410000
0d
0j
0f
1Q
0z
0u
0t
0v
0x!
0v!
1<"
0+"
b0 ,"
b0 -"
0G"
b0 H"
b0 I"
#420000
0Q
0<"
#430000
1Q
1<"
#440000
0Q
0<"
